{
  "version": "0.1",
  "language": "he",
  "category_id": "mythology_fantasy",
  "category_name": "מיתולוגיה ופנטזיה",
  "generation_guidelines": {
    "entries_count": 50,
    "clues_per_entry": 10,
    "grid_size": 32,
    "first_clue": "category descriptor",
    "no_letter_based_clues": true,
    "no_punctuation_in_clues": true,
    "grid_should_be_shuffled_at_runtime": true,
    "correct_answer_position": "first_for_validation_only"
  },
  "entries": [
    {
      "id": "mythology_fantasy_001",
      "category_id": "mythology_fantasy",
      "category_name": "מיתולוגיה ופנטזיה",
      "answer": "דרקון",
      "answer_niqqud": "דְּרָקוֹן",
      "clues": [
        "אֲנִי מֵעוֹלָם דִּמְיוֹנִי אוֹ מִיתוֹלוֹגִי",
        "אֲנִי יְצוּר עָצוּם שֶׁמּוֹפִיעַ בְּאַגָּדוֹת רַבּוֹת",
        "לְעִתִּים יֵשׁ לִי קַשְׂקַשִּׂים קְשִׁיחִים וְטְפָרִים חַדִּים",
        "בְּסִפּוּרִים רַבִּים אֲנִי שׁוֹמֵר עַל אוֹצָר",
        "הַכְּנָפַיִם שֶׁלִּי יְכוֹלוֹת לְהַטִּיל צֵל גָּדוֹל מְאֹד",
        "לְעִתִּים אֲנִי יוֹרֵק לֶהָבוֹת מִפִּי",
        "גִּבּוֹרִים מְפַחֲדִים מִמֶּנִּי וּמְנַסִּים לְנַצֵּחַ אוֹתִי",
        "אֲנִי מְסַמֵּל כֹּחַ פְּרָאִי וְחָכְמָה עַתִּיקָה לְעִתִּים",
        "אֲנִי גָּדוֹל יוֹתֵר מֵרוֹב הַחַיּוֹת בַּדִּמְיוֹן",
        "זֶה יְצוּר מְכֻנָּף שֶׁנּוֹשֵׁף אֵשׁ בְּאַגָּדוֹת"
      ],
      "grid": [
        "דרקון",
        "חד קרן",
        "אוצר מקולל",
        "פיה",
        "מבוך",
        "מכשפה",
        "שער קסום",
        "קוסם",
        "ספר לחשים",
        "שדון",
        "שיקוי קסמים",
        "גמד",
        "טבעת קסומה",
        "ענק",
        "שרביט קסמים",
        "טרול",
        "חרב קסומה",
        "גובלין",
        "מלכה",
        "אורק",
        "מלך",
        "אלף",
        "נסיכה",
        "בת ים",
        "נסיך",
        "קנטאור",
        "אביר",
        "מינוטאור",
        "ויקינג",
        "קיקלופ",
        "אלה יוונית",
        "גריפין"
      ]
    },
    {
      "id": "mythology_fantasy_002",
      "category_id": "mythology_fantasy",
      "category_name": "מיתולוגיה ופנטזיה",
      "answer": "חד קרן",
      "answer_niqqud": "חַד קֶרֶן",
      "clues": [
        "אֲנִי מֵעוֹלָם דִּמְיוֹנִי אוֹ מִיתוֹלוֹגִי",
        "אֲנִי יְצוּר עָדִין שֶׁמַּזְכִּיר סוּס לָבָן",
        "בְּמֶרְכַּז הַמֵּצַח שֶׁלִּי יֵשׁ בְּלִיטָה מְסֻבֶּבֶת",
        "אֲנִי מְסַמֵּל טֹהַר וְקֶסֶם בְּסִפּוּרִים רַבִּים",
        "יְלָדִים מְדַמְיְנִים אוֹתִי בְּצִבְעֵי קֶשֶׁת לְעִתִּים",
        "קָשֶׁה מְאֹד לִתְפֹּס אוֹתִי בְּאַגָּדוֹת",
        "אֲנִי מוֹפִיעַ לְעִתִּים בְּיַעַר שָׁקֵט וּמְכֻשָּׁף",
        "הַמַּרְאֶה שֶׁלִּי נֶחְשָׁב יָפֶה וּנְדִיר",
        "הַקֶּרֶן שֶׁלִּי נֶחְשֶׁבֶת בַּעֲלַת כֹּחַ פֶּלֶא",
        "זֶה סוּס דִּמְיוֹנִי עִם קֶרֶן אַחַת בַּמֵּצַח"
      ],
      "grid": [
        "חד קרן",
        "פיה",
        "דרקון",
        "מכשפה",
        "אוצר מקולל",
        "קוסם",
        "מבוך",
        "שדון",
        "שער קסום",
        "גמד",
        "ספר לחשים",
        "ענק",
        "שיקוי קסמים",
        "טרול",
        "טבעת קסומה",
        "גובלין",
        "שרביט קסמים",
        "אורק",
        "חרב קסומה",
        "אלף",
        "מלכה",
        "בת ים",
        "מלך",
        "קנטאור",
        "נסיכה",
        "מינוטאור",
        "נסיך",
        "קיקלופ",
        "אביר",
        "גריפין",
        "ויקינג",
        "פניקס"
      ]
    },
    {
      "id": "mythology_fantasy_003",
      "category_id": "mythology_fantasy",
      "category_name": "מיתולוגיה ופנטזיה",
      "answer": "פיה",
      "answer_niqqud": "פֵּיָה",
      "clues": [
        "אֲנִי מֵעוֹלָם דִּמְיוֹנִי אוֹ מִיתוֹלוֹגִי",
        "אֲנִי יְצוּרָה קְטַנָּה וַעֲדִינָה בַּסִּפּוּרִים",
        "לְעִתִּים יֵשׁ לִי כְּנָפַיִם שְׁקוּפוֹת",
        "אֲנִי קְשׁוּרָה לְאַבְקָה מְנַצְנֶצֶת וּמַעֲשֵׂי פֶּלֶא",
        "אֲנִי יְכוֹלָה לְהוֹפִיעַ בְּיַעַר אוֹ לְיַד פֶּרַח",
        "בְּסִפּוּרִים לִילָדִים אֲנִי עוֹזֶרֶת לְגִבּוֹרִים לְעִתִּים",
        "הַקּוֹל שֶׁלִּי נִדְמֶה קָטָן וְקַל",
        "אֲנִי מְסַמֶּלֶת קֶסֶם עָדִין וְטוּב לֵב",
        "בְּצִיּוּרִים אֲנִי מוֹפִיעָה עִם שִׂמְלָה קְטַנָּה",
        "זֶה יְצוּרָה קְטַנָּה עִם כְּנָפַיִם וְכֹחוֹת פֶּלֶא"
      ],
      "grid": [
        "פיה",
        "מכשפה",
        "חד קרן",
        "קוסם",
        "דרקון",
        "שדון",
        "אוצר מקולל",
        "גמד",
        "מבוך",
        "ענק",
        "שער קסום",
        "טרול",
        "ספר לחשים",
        "גובלין",
        "שיקוי קסמים",
        "אורק",
        "טבעת קסומה",
        "אלף",
        "שרביט קסמים",
        "בת ים",
        "חרב קסומה",
        "קנטאור",
        "מלכה",
        "מינוטאור",
        "מלך",
        "קיקלופ",
        "נסיכה",
        "גריפין",
        "נסיך",
        "פניקס",
        "אביר",
        "הידרה"
      ]
    },
    {
      "id": "mythology_fantasy_004",
      "category_id": "mythology_fantasy",
      "category_name": "מיתולוגיה ופנטזיה",
      "answer": "מכשפה",
      "answer_niqqud": "מְכַשֵּׁפָה",
      "clues": [
        "אֲנִי מֵעוֹלָם דִּמְיוֹנִי אוֹ מִיתוֹלוֹגִי",
        "אֲנִי דְּמוּת שֶׁיּוֹדַעַת לְהַשְׁפִּיעַ עַל הַמְּצִיאוּת בְּדֶרֶךְ פֶּלֶא",
        "לְעִתִּים מְצַיְּרִים אוֹתִי עִם כּוֹבַע מְחֻדָּד",
        "קְדֵרָה מְעַשֶּׁנֶת וְסֵפֶר סוֹדוֹת קְשׁוּרִים אֵלַי",
        "בְּאַגָּדוֹת אֲנִי יְכוֹלָה לִהְיוֹת טוֹבָה אוֹ מַפְחִידָה",
        "לְעִתִּים אֲנִי רוֹכֶבֶת עַל מַטְאטֵא בַּלַּיְלָה",
        "חַיַּת לַיְלָה שְׁחֹרָה מְלַוָּה אוֹתִי לְעִתִּים",
        "אֲנִי מְעָרְבֶּבֶת רְכִיבִים מוּזָרִים כְּדֵי לִיצֹר תּוֹצָאָה מֻפְלָאָה",
        "אֲנָשִׁים בַּסִּפּוּר נִזְהָרִים מִן הַקְּלָלָה שֶׁלִּי",
        "זֶה דְּמוּת קֶסֶם שֶׁמְּצוּיֶּרֶת לְעִתִּים עִם כּוֹבַע וּמַטְאטֵא"
      ],
      "grid": [
        "מכשפה",
        "קוסם",
        "פיה",
        "שדון",
        "חד קרן",
        "גמד",
        "דרקון",
        "ענק",
        "אוצר מקולל",
        "טרול",
        "מבוך",
        "גובלין",
        "שער קסום",
        "אורק",
        "ספר לחשים",
        "אלף",
        "שיקוי קסמים",
        "בת ים",
        "טבעת קסומה",
        "קנטאור",
        "שרביט קסמים",
        "מינוטאור",
        "חרב קסומה",
        "קיקלופ",
        "מלכה",
        "גריפין",
        "מלך",
        "פניקס",
        "נסיכה",
        "הידרה",
        "נסיך",
        "מדוזה"
      ]
    },
    {
      "id": "mythology_fantasy_005",
      "category_id": "mythology_fantasy",
      "category_name": "מיתולוגיה ופנטזיה",
      "answer": "קוסם",
      "answer_niqqud": "קוֹסֵם",
      "clues": [
        "אֲנִי מֵעוֹלָם דִּמְיוֹנִי אוֹ מִיתוֹלוֹגִי",
        "אֲנִי דְּמוּת שֶׁיּוֹדַעַת לְבַצֵּעַ מַעֲשֵׂי פֶּלֶא",
        "לְעִתִּים אֲנִי לוֹבֵשׁ גְּלִימָה אֲרֻכָּה",
        "סֵפֶר סוֹדוֹת וּכְלִי מֻפְלָא קְשׁוּרִים אֵלַי",
        "בְּסִפּוּרִים אֲנִי יָכוֹל לְהַעֲלִים לְשַׁנּוֹת וּלְהוֹפִיעַ",
        "אֲנִי מְלַמֵּד גִּבּוֹרִים צְעִירִים לְעִתִּים",
        "הַמִּלִּים שֶׁלִּי עֲלוּלוֹת לִפְעֹל כְּמוֹ כֹּחַ נִסְתָּר",
        "אֲנִי מוֹפִיעַ בְּמִגְדָּלִים בְּאַרְמוֹנוֹת וּבְיַעֲרוֹת",
        "לְעִתִּים זָקָן אָרֹךְ וְעֵינַיִם חַכָּמוֹת מְאַפְיְנִים אוֹתִי",
        "זֶה בַּעַל כֹּחוֹת פֶּלֶא שֶׁמְּטִיל לְחָשִׁים"
      ],
      "grid": [
        "קוסם",
        "שדון",
        "מכשפה",
        "גמד",
        "פיה",
        "ענק",
        "חד קרן",
        "טרול",
        "דרקון",
        "גובלין",
        "אוצר מקולל",
        "אורק",
        "מבוך",
        "אלף",
        "שער קסום",
        "בת ים",
        "ספר לחשים",
        "קנטאור",
        "שיקוי קסמים",
        "מינוטאור",
        "טבעת קסומה",
        "קיקלופ",
        "שרביט קסמים",
        "גריפין",
        "חרב קסומה",
        "פניקס",
        "מלכה",
        "הידרה",
        "מלך",
        "מדוזה",
        "נסיכה",
        "ספינקס"
      ]
    },
    {
      "id": "mythology_fantasy_006",
      "category_id": "mythology_fantasy",
      "category_name": "מיתולוגיה ופנטזיה",
      "answer": "שדון",
      "answer_niqqud": "שֵׁדוֹן",
      "clues": [
        "אֲנִי מֵעוֹלָם דִּמְיוֹנִי אוֹ מִיתוֹלוֹגִי",
        "אֲנִי יְצוּר קָטָן וְעָרְמוּמִי בְּסִפּוּרִים",
        "לְעִתִּים אֲנִי גָּר בְּיַעַר אוֹ בְּמַחֲבֹא סוֹדִי",
        "אֲנִי יָכוֹל לַעֲשׂוֹת תַּעֲלוּלִים קְטַנִּים",
        "הָאוזְנַיִם שֶׁלִּי מְצוּיָּרוֹת לְעִתִּים מְחֻדָּדוֹת",
        "אֲנִי אֵינִי בְּדֶרֶךְ כְּלָל גִּבּוֹר גָּדוֹל וְרִשְׁמִי",
        "בְּסִפּוּרִים אֲנִי יָכוֹל לְהַטְעוֹת אֲנָשִׁים",
        "הַמַּרְאֶה שֶׁלִּי קָטָן מוּזָר וּמְשַׁעֲשֵׁעַ",
        "לְעִתִּים אֲנִי שׁוֹמֵר עַל אוֹצָר אוֹ עַל סוֹד",
        "זֶה יְצוּר קָטָן מֵאַגָּדוֹת שֶׁאוֹהֵב תַּעֲלוּלִים"
      ],
      "grid": [
        "שדון",
        "גמד",
        "קוסם",
        "ענק",
        "מכשפה",
        "טרול",
        "פיה",
        "גובלין",
        "חד קרן",
        "אורק",
        "דרקון",
        "אלף",
        "אוצר מקולל",
        "בת ים",
        "מבוך",
        "קנטאור",
        "שער קסום",
        "מינוטאור",
        "ספר לחשים",
        "קיקלופ",
        "שיקוי קסמים",
        "גריפין",
        "טבעת קסומה",
        "פניקס",
        "שרביט קסמים",
        "הידרה",
        "חרב קסומה",
        "מדוזה",
        "מלכה",
        "ספינקס",
        "מלך",
        "פגסוס"
      ]
    },
    {
      "id": "mythology_fantasy_007",
      "category_id": "mythology_fantasy",
      "category_name": "מיתולוגיה ופנטזיה",
      "answer": "גמד",
      "answer_niqqud": "גַּמָּד",
      "clues": [
        "אֲנִי מֵעוֹלָם דִּמְיוֹנִי אוֹ מִיתוֹלוֹגִי",
        "אֲנִי דְּמוּת קְטַנָּה וַחֲזָקָה בְּעולמות דִּמְיוֹן",
        "לְעִתִּים אֲנִי חַי מִתַּחַת לָאֲדָמָה אוֹ בְּהָרִים",
        "אֲנִי מְזֹהֶה עִם עֲבוֹדַת מַתֶּכֶת וְאֲבָנִים יְקָרוֹת",
        "זָקָן עָב וְגַרְזֶן מוֹפִיעִים אִתִּי לְעִתִּים",
        "אֲנִי עַקְשָׁן וְנֶאֱמָן בְּסִפּוּרִים רַבִּים",
        "הַגֹּבַהַּ שֶׁלִּי נָמוּךְ אֲבָל הַכֹּחַ גָּדוֹל",
        "אֲנִי אוֹהֵב מַחְצַבִּים וְאוֹצָרוֹת לְעִתִּים",
        "בְּפַנְטָזְיָה אֲנִי חֵלֶק מֵעַם עַתִּיק וְקָשׁוּחַ",
        "זֶה יְצוּר קָטָן וְחָזָק שֶׁקָּשׁוּר לְמַכְרוֹת וּלְזָקָן"
      ],
      "grid": [
        "גמד",
        "ענק",
        "שדון",
        "טרול",
        "קוסם",
        "גובלין",
        "מכשפה",
        "אורק",
        "פיה",
        "אלף",
        "חד קרן",
        "בת ים",
        "דרקון",
        "קנטאור",
        "אוצר מקולל",
        "מינוטאור",
        "מבוך",
        "קיקלופ",
        "שער קסום",
        "גריפין",
        "ספר לחשים",
        "פניקס",
        "שיקוי קסמים",
        "הידרה",
        "טבעת קסומה",
        "מדוזה",
        "שרביט קסמים",
        "ספינקס",
        "חרב קסומה",
        "פגסוס",
        "מלכה",
        "קרברוס"
      ]
    },
    {
      "id": "mythology_fantasy_008",
      "category_id": "mythology_fantasy",
      "category_name": "מיתולוגיה ופנטזיה",
      "answer": "ענק",
      "answer_niqqud": "עֲנָק",
      "clues": [
        "אֲנִי מֵעוֹלָם דִּמְיוֹנִי אוֹ מִיתוֹלוֹגִי",
        "אֲנִי דְּמוּת גְּדוֹלָה מְאֹד מֵהָאָדָם",
        "הַצְּעָדִים שֶׁלִּי יְכוֹלִים לְהַרְעִיד אֶת הָאֲדָמָה",
        "בְּאַגָּדוֹת אֲנִי גָּר לְעִתִּים בְּטִירָה גְּבוֹהָה אוֹ בְּהָר",
        "אֲנִי יָכוֹל לְהָרִים דְּבָרִים שֶׁבְּנֵי אָדָם לֹא יְכוֹלִים",
        "הַקּוֹל שֶׁלִּי יְכוֹל לִהְיוֹת עָמֹק וּמְרַעֵם",
        "לְעִתִּים אֲנִי מְפַחִיד אֲבָל לֹא תָּמִיד רָע",
        "גִּבּוֹר קָטָן מְנַסֶּה לְהַעֲרִים עָלַי בְּסִפּוּרִים",
        "הַמִּדָּה שֶׁלִּי הִיא הַמַּאֲפֵן הַבּוֹלֵט בְּיוֹתֵר",
        "זֶה דְּמוּת עֲנָקִית שֶׁגְּבוֹהָה מִבַּיִת לְעִתִּים"
      ],
      "grid": [
        "ענק",
        "טרול",
        "גמד",
        "גובלין",
        "שדון",
        "אורק",
        "קוסם",
        "אלף",
        "מכשפה",
        "בת ים",
        "פיה",
        "קנטאור",
        "חד קרן",
        "מינוטאור",
        "דרקון",
        "קיקלופ",
        "אוצר מקולל",
        "גריפין",
        "מבוך",
        "פניקס",
        "שער קסום",
        "הידרה",
        "ספר לחשים",
        "מדוזה",
        "שיקוי קסמים",
        "ספינקס",
        "טבעת קסומה",
        "פגסוס",
        "שרביט קסמים",
        "קרברוס",
        "חרב קסומה",
        "קרקן"
      ]
    },
    {
      "id": "mythology_fantasy_009",
      "category_id": "mythology_fantasy",
      "category_name": "מיתולוגיה ופנטזיה",
      "answer": "טרול",
      "answer_niqqud": "טְרוֹל",
      "clues": [
        "אֲנִי מֵעוֹלָם דִּמְיוֹנִי אוֹ מִיתוֹלוֹגִי",
        "אֲנִי יְצוּר גַּס וְחָזָק מֵאַגָּדוֹת צְפוֹנִיּוֹת לְעִתִּים",
        "לְעִתִּים אֲנִי גָּר מִתַּחַת לְגֶשֶׁר",
        "הַמַּרְאֶה שֶׁלִּי מְכֹעָר וּמְאיים בְּסִפּוּרִים רַבִּים",
        "אֲנִי עָלוּל לַחְסֹם דֶּרֶךְ לְעוֹבְרִים וְשָׁבִים",
        "לְעִתִּים אֲנִי פָּחוֹת חָכָם מִן הַגִּבּוֹר",
        "אוֹר הַיּוֹם יָכוֹל לִהְיוֹת מְסֻכָּן לִי בְּאַגָּדוֹת מְסֻיָּמוֹת",
        "אֲנִי קָשׁוּר לְמְקוֹמוֹת קָרִים וַחֲשׁוּכִים",
        "הַגּוּף שֶׁלִּי גָּדוֹל וְכָבֵד לְעִתִּים",
        "זֶה יְצוּר מְפַחִיד שֶׁמְּחַכֶּה לְעִתִּים מִתַּחַת לְגֶשֶׁר"
      ],
      "grid": [
        "טרול",
        "גובלין",
        "ענק",
        "אורק",
        "גמד",
        "אלף",
        "שדון",
        "בת ים",
        "קוסם",
        "קנטאור",
        "מכשפה",
        "מינוטאור",
        "פיה",
        "קיקלופ",
        "חד קרן",
        "גריפין",
        "דרקון",
        "פניקס",
        "אוצר מקולל",
        "הידרה",
        "מבוך",
        "מדוזה",
        "שער קסום",
        "ספינקס",
        "ספר לחשים",
        "פגסוס",
        "שיקוי קסמים",
        "קרברוס",
        "טבעת קסומה",
        "קרקן",
        "שרביט קסמים",
        "בזיליסק"
      ]
    },
    {
      "id": "mythology_fantasy_010",
      "category_id": "mythology_fantasy",
      "category_name": "מיתולוגיה ופנטזיה",
      "answer": "גובלין",
      "answer_niqqud": "גּוֹבְּלִין",
      "clues": [
        "אֲנִי מֵעוֹלָם דִּמְיוֹנִי אוֹ מִיתוֹלוֹגִי",
        "אֲנִי יְצוּר קָטָן וְלֹא נָעִים מֵעוֹלָמוֹת פַנְטָזְיָה",
        "לְעִתִּים אֲנִי מוֹפִיעַ בְּקְבוּצוֹת גְּדוֹלוֹת",
        "הָעור שֶׁלִּי מְצוּיָּר לְעִתִּים בְּיָרֹק אוֹ אָפֹר",
        "אֲנִי עָרוּם וְרַעֲשָׁן בְּסִפּוּרִים רַבִּים",
        "מְחִילּוֹת מְעָרוֹת וּמַחֲסָנֵי אוֹצָר קְשׁוּרִים אֵלַי",
        "אֲנִי יָכוֹל לִהְיוֹת אוֹיֵב קָטָן בִּתְחִלַּת הַרְפַּתְקָה",
        "לְעִתִּים אֲנִי נוֹשֵׂא סַכִּין חָלוּד אוֹ מַקֵּל",
        "הַפָּנִים שֶׁלִּי מְצוּיָּרוֹת לְעִתִּים עִם אַף חַד",
        "זֶה יְצוּר פַנְטָזְיָה קָטָן יָרֹק וּמְעַצְבֵּן לְעִתִּים"
      ],
      "grid": [
        "גובלין",
        "אורק",
        "טרול",
        "אלף",
        "ענק",
        "בת ים",
        "גמד",
        "קנטאור",
        "שדון",
        "מינוטאור",
        "קוסם",
        "קיקלופ",
        "מכשפה",
        "גריפין",
        "פיה",
        "פניקס",
        "חד קרן",
        "הידרה",
        "דרקון",
        "מדוזה",
        "אוצר מקולל",
        "ספינקס",
        "מבוך",
        "פגסוס",
        "שער קסום",
        "קרברוס",
        "ספר לחשים",
        "קרקן",
        "שיקוי קסמים",
        "בזיליסק",
        "טבעת קסומה",
        "גולם"
      ]
    },
    {
      "id": "mythology_fantasy_011",
      "category_id": "mythology_fantasy",
      "category_name": "מיתולוגיה ופנטזיה",
      "answer": "אורק",
      "answer_niqqud": "אוֹרְק",
      "clues": [
        "אֲנִי מֵעוֹלָם דִּמְיוֹנִי אוֹ מִיתוֹלוֹגִי",
        "אֲנִי יְצוּר לוֹחֵם וְקָשׁוּחַ בְּעוֹלָמוֹת פַנְטָזְיָה",
        "לְעִתִּים אֲנִי מוֹפִיעַ בְּצָבָא גָּדוֹל וְרַעֲשָׁנִי",
        "הַמַּרְאֶה שֶׁלִּי יָכוֹל לִהְיוֹת גַּס וּמְאַיֵּם",
        "אֲנִי נוֹשֵׂא גַּרְזֶן חֲנִית אוֹ חֶרֶב לְעִתִּים",
        "בְּסִפּוּרִים רַבִּים אֲנִי מְשַׁרֵּת כֹּחַ רָע",
        "הַכֹּחַ הַגּוּפָנִי שֶׁלִּי בּוֹלֵט יוֹתֵר מֵעִדּוּן",
        "אֲנִי מוֹפִיעַ לְעִתִּים בְּמִבְצָרִים חֲשׁוּכִים",
        "הַקּוֹל שֶׁלִּי מְתֹאָר כִּצְרִידָה גַּסָּה לְעִתִּים",
        "זֶה לוֹחֵם פַנְטָזְיָה גַּס וְחָזָק מִצְּבָא אַפֵל"
      ],
      "grid": [
        "אורק",
        "אלף",
        "גובלין",
        "בת ים",
        "טרול",
        "קנטאור",
        "ענק",
        "מינוטאור",
        "גמד",
        "קיקלופ",
        "שדון",
        "גריפין",
        "קוסם",
        "פניקס",
        "מכשפה",
        "הידרה",
        "פיה",
        "מדוזה",
        "חד קרן",
        "ספינקס",
        "דרקון",
        "פגסוס",
        "אוצר מקולל",
        "קרברוס",
        "מבוך",
        "קרקן",
        "שער קסום",
        "בזיליסק",
        "ספר לחשים",
        "גולם",
        "שיקוי קסמים",
        "ערפד"
      ]
    },
    {
      "id": "mythology_fantasy_012",
      "category_id": "mythology_fantasy",
      "category_name": "מיתולוגיה ופנטזיה",
      "answer": "אלף",
      "answer_niqqud": "אֶלְף",
      "clues": [
        "אֲנִי מֵעוֹלָם דִּמְיוֹנִי אוֹ מִיתוֹלוֹגִי",
        "אֲנִי בֶּן לְעַם עָדִין וְעַתִּיק בְּעוֹלָמוֹת פַנְטָזְיָה",
        "הָאוזְנַיִם שֶׁלִּי מְצוּיָּרוֹת לְעִתִּים מְחֻדָּדוֹת",
        "אֲנִי מְזֹהֶה עִם יֹפִי חָכְמָה וְחַיִּים אֲרֻכִּים",
        "לְעִתִּים אֲנִי גָּר בְּיַעַר מֻפְלָא אוֹ בְּעִיר מְזוֹהֶרֶת",
        "קֶשֶׁת דַּקָּה וְתְנוּעָה שְׁקֵטָה קְשׁוּרִים אֵלַי לְעִתִּים",
        "אֲנִי נִרְאֶה כְּמוֹ אָדָם אֲבָל עָדִין וְאַחֵר",
        "בְּסִפּוּרִים אֲנִי חַי דּוֹרוֹת רַבִּים",
        "הַתַּרְבּוּת שֶׁלִּי מְתֹאָרֶת כְּיָפָה וּמֻשְׁלֶמֶת לְעִתִּים",
        "זֶה יְצוּר דְּמוּי אָדָם עַדִּין עִם אוזְנַיִם מְחֻדָּדוֹת"
      ],
      "grid": [
        "אלף",
        "בת ים",
        "אורק",
        "קנטאור",
        "גובלין",
        "מינוטאור",
        "טרול",
        "קיקלופ",
        "ענק",
        "גריפין",
        "גמד",
        "פניקס",
        "שדון",
        "הידרה",
        "קוסם",
        "מדוזה",
        "מכשפה",
        "ספינקס",
        "פיה",
        "פגסוס",
        "חד קרן",
        "קרברוס",
        "דרקון",
        "קרקן",
        "אוצר מקולל",
        "בזיליסק",
        "מבוך",
        "גולם",
        "שער קסום",
        "ערפד",
        "ספר לחשים",
        "איש זאב"
      ]
    },
    {
      "id": "mythology_fantasy_013",
      "category_id": "mythology_fantasy",
      "category_name": "מיתולוגיה ופנטזיה",
      "answer": "בת ים",
      "answer_niqqud": "בַּת יָם",
      "clues": [
        "אֲנִי מֵעוֹלָם דִּמְיוֹנִי אוֹ מִיתוֹלוֹגִי",
        "אֲנִי יְצוּרָה שֶׁחֶלְקָהּ הָעֶלְיוֹן דּוֹמֶה לְאָדָם",
        "הַחֵלֶק הַתַּחְתּוֹן שֶׁלִּי דּוֹמֶה לְזָנָב דָּג",
        "אֲנִי חַיָּה בְּמַיִם עֲמֻקִּים בְּסִפּוּרִים רַבִּים",
        "שִׁירָה יָפָה וּסוֹדוֹת מַעֲמָקִים קְשׁוּרִים אֵלַי",
        "מַלָּחִים מְסַפְּרִים עָלַי בְּאַגָּדוֹת יָם",
        "הַשֵּׂעָר שֶׁלִּי מְצוּיָּר לְעִתִּים אָרֹךְ וְזוֹרֵם",
        "אֲנִי מְחַבֶּרֶת בֵּין עוֹלַם הָאָדָם לְעוֹלַם הַמַּיִם",
        "לְעִתִּים אֲנִי מוֹפִיעָה עַל סֶלַע לְיַד גַּלִּים",
        "זֶה יְצוּרָה דִּמְיוֹנִית שֶׁחֶצְיָה אִשָּׁה וְחֶצְיָה דָּג"
      ],
      "grid": [
        "בת ים",
        "קנטאור",
        "אלף",
        "מינוטאור",
        "אורק",
        "קיקלופ",
        "גובלין",
        "גריפין",
        "טרול",
        "פניקס",
        "ענק",
        "הידרה",
        "גמד",
        "מדוזה",
        "שדון",
        "ספינקס",
        "קוסם",
        "פגסוס",
        "מכשפה",
        "קרברוס",
        "פיה",
        "קרקן",
        "חד קרן",
        "בזיליסק",
        "דרקון",
        "גולם",
        "אוצר מקולל",
        "ערפד",
        "מבוך",
        "איש זאב",
        "שער קסום",
        "מומיה"
      ]
    },
    {
      "id": "mythology_fantasy_014",
      "category_id": "mythology_fantasy",
      "category_name": "מיתולוגיה ופנטזיה",
      "answer": "קנטאור",
      "answer_niqqud": "קֶנְטָאוּר",
      "clues": [
        "אֲנִי מֵעוֹלָם דִּמְיוֹנִי אוֹ מִיתוֹלוֹגִי",
        "אֲנִי יְצוּר שֶׁמְּחַבֵּר גּוּף אָדָם וְגוף סוּס",
        "הַחֵלֶק הָעֶלְיוֹן שֶׁלִּי דּוֹמֶה לְאָדָם",
        "הַחֵלֶק הַתַּחְתּוֹן שֶׁלִּי רָץ עַל אַרְבַּע רַגְלַיִם",
        "אֲנִי מוֹפִיעַ בְּסִפּוּרִים עַתִּיקִים מִסְּבִיבַת הַיָּם הַתִּיכוֹן",
        "לְעִתִּים אֲנִי מְתֹאָר כְּלוֹחֵם אוֹ מוֹרֶה חָכָם",
        "קֶשֶׁת וְחִצִּים קְשׁוּרִים אֵלַי בְּדִמְיוֹן רַבִּים",
        "אֲנִי יָכוֹל לָרוּץ בִּשְׂדֵה קְרָב מַהֵר מֵאָדָם",
        "הַצּוּרָה שֶׁלִּי הִיא שִׁלּוּב שֶׁל תַּרְבּוּת וּפֶרֶא",
        "זֶה יְצוּר מִיתוֹלוֹגִי שֶׁחֶצְיוֹ אָדָם וְחֶצְיוֹ סוּס"
      ],
      "grid": [
        "קנטאור",
        "מינוטאור",
        "בת ים",
        "קיקלופ",
        "אלף",
        "גריפין",
        "אורק",
        "פניקס",
        "גובלין",
        "הידרה",
        "טרול",
        "מדוזה",
        "ענק",
        "ספינקס",
        "גמד",
        "פגסוס",
        "שדון",
        "קרברוס",
        "קוסם",
        "קרקן",
        "מכשפה",
        "בזיליסק",
        "פיה",
        "גולם",
        "חד קרן",
        "ערפד",
        "דרקון",
        "איש זאב",
        "אוצר מקולל",
        "מומיה",
        "מבוך",
        "זומבי"
      ]
    },
    {
      "id": "mythology_fantasy_015",
      "category_id": "mythology_fantasy",
      "category_name": "מיתולוגיה ופנטזיה",
      "answer": "מינוטאור",
      "answer_niqqud": "מִינוֹטָאוּר",
      "clues": [
        "אֲנִי מֵעוֹלָם דִּמְיוֹנִי אוֹ מִיתוֹלוֹגִי",
        "אֲנִי יְצוּר מַפְחִיד עִם רֹאשׁ שֶׁל בְּהֵמָה חֲזָקָה",
        "הַגּוּף שֶׁלִּי דּוֹמֶה לְאָדָם גָּדוֹל",
        "אֲנִי מְקֻשָּׁר לְמִבְנֶה מְבֻלְבָּל וְסוֹדִי",
        "בְּסִפּוּר עַתִּיק גִּבּוֹר נִכְנָס לְחַפֵּשׂ אוֹתִי",
        "הַקְּרָנַיִם שֶׁלִּי מְאַפְיְנוֹת אוֹתִי",
        "אֲנִי מְסַמֵּל פַּחַד שֶׁמִּתְחַבֵּא בְּתוֹךְ מִסְתּוֹרִין",
        "לְעִתִּים מְדַמְיְנִים אוֹתִי כְּשׁוֹמֵר שֶׁאִי אֶפְשָׁר לַעֲקֹף",
        "הַשְּׁאָגָה שֶׁלִּי מְמַלְּאָה מַעֲבָרִים אֲפֵלִים",
        "זֶה יְצוּר עַתִּיק עִם רֹאשׁ שׁוֹר וְגוף אָדָם"
      ],
      "grid": [
        "מינוטאור",
        "קיקלופ",
        "קנטאור",
        "גריפין",
        "בת ים",
        "פניקס",
        "אלף",
        "הידרה",
        "אורק",
        "מדוזה",
        "גובלין",
        "ספינקס",
        "טרול",
        "פגסוס",
        "ענק",
        "קרברוס",
        "גמד",
        "קרקן",
        "שדון",
        "בזיליסק",
        "קוסם",
        "גולם",
        "מכשפה",
        "ערפד",
        "פיה",
        "איש זאב",
        "חד קרן",
        "מומיה",
        "דרקון",
        "זומבי",
        "אוצר מקולל",
        "שלד חי"
      ]
    },
    {
      "id": "mythology_fantasy_016",
      "category_id": "mythology_fantasy",
      "category_name": "מיתולוגיה ופנטזיה",
      "answer": "קיקלופ",
      "answer_niqqud": "קִיקְלוֹפּ",
      "clues": [
        "אֲנִי מֵעוֹלָם דִּמְיוֹנִי אוֹ מִיתוֹלוֹגִי",
        "אֲנִי יְצוּר עָצוּם מִסִּפּוּרִים עַתִּיקִים",
        "יֵשׁ לִי עַיִן אַחַת בִּמְקוֹם שְׁתַּיִם",
        "לְעִתִּים אֲנִי גָּר בִּמְעָרָה רְחוֹקָה",
        "הַכֹּחַ שֶׁלִּי גָּדוֹל אֲבָל הַתְּחִכּוּם לֹא תָּמִיד",
        "גִּבּוֹר חָכָם יָכוֹל לְנַצֵּחַ אוֹתִי בְּתַחְבּוּלָה",
        "אֲנִי מוֹפִיעַ בְּאַגָּדוֹת שֶׁל מַסָּעוֹת וְיַם",
        "הַמַּרְאֶה שֶׁלִּי מִיָּד מְזֹהֶה בִּגְלַל הַפָּנִים",
        "לְעִתִּים אֲנִי רוֹעֶה עֲדָרִים בְּסִפּוּר",
        "זֶה יְצוּר מִיתוֹלוֹגִי עָצוּם בַּעַל עַיִן אַחַת"
      ],
      "grid": [
        "קיקלופ",
        "גריפין",
        "מינוטאור",
        "פניקס",
        "קנטאור",
        "הידרה",
        "בת ים",
        "מדוזה",
        "אלף",
        "ספינקס",
        "אורק",
        "פגסוס",
        "גובלין",
        "קרברוס",
        "טרול",
        "קרקן",
        "ענק",
        "בזיליסק",
        "גמד",
        "גולם",
        "שדון",
        "ערפד",
        "קוסם",
        "איש זאב",
        "מכשפה",
        "מומיה",
        "פיה",
        "זומבי",
        "חד קרן",
        "שלד חי",
        "דרקון",
        "רוח רפאים"
      ]
    },
    {
      "id": "mythology_fantasy_017",
      "category_id": "mythology_fantasy",
      "category_name": "מיתולוגיה ופנטזיה",
      "answer": "גריפין",
      "answer_niqqud": "גְּרִיפִין",
      "clues": [
        "אֲנִי מֵעוֹלָם דִּמְיוֹנִי אוֹ מִיתוֹלוֹגִי",
        "אֲנִי יְצוּר מְשֻׁלָּב מִשְּׁתֵּי חַיּוֹת מְרַשִּׁימוֹת",
        "הַחֵלֶק הַקִּדְמִי שֶׁלִּי מַזְכִּיר עוֹף טוֹרֵף",
        "הַחֵלֶק הָאֲחוֹרִי שֶׁלִּי מַזְכִּיר חַיָּה מְלָכוּתִית",
        "כְּנָפַיִם טְפָרִים וּמַקּוֹר חָד קְשׁוּרִים אֵלַי",
        "אֲנִי מְסַמֵּל שְׁמִירָה עֹז וַאֲצִילוּת",
        "לְעִתִּים אֲנִי שׁוֹמֵר עַל אוֹצָרוֹת אוֹ עַל מְקוֹמוֹת קְדוֹשִׁים",
        "אֲנִי מוֹפִיעַ בְּסִמְלֵי אֲצֻלָּה וּבְאַגָּדוֹת עַתִּיקוֹת",
        "הַמַּרְאֶה שֶׁלִּי מְחַבֵּר שָׁמַיִם וִיבָּשָׁה",
        "זֶה יְצוּר עִם רֹאשׁ וּכְנָפַיִם שֶׁל עַיִט וְגוּף שֶׁל אַרְיֵה"
      ],
      "grid": [
        "גריפין",
        "פניקס",
        "קיקלופ",
        "הידרה",
        "מינוטאור",
        "מדוזה",
        "קנטאור",
        "ספינקס",
        "בת ים",
        "פגסוס",
        "אלף",
        "קרברוס",
        "אורק",
        "קרקן",
        "גובלין",
        "בזיליסק",
        "טרול",
        "גולם",
        "ענק",
        "ערפד",
        "גמד",
        "איש זאב",
        "שדון",
        "מומיה",
        "קוסם",
        "זומבי",
        "מכשפה",
        "שלד חי",
        "פיה",
        "רוח רפאים",
        "חד קרן",
        "מלאך"
      ]
    },
    {
      "id": "mythology_fantasy_018",
      "category_id": "mythology_fantasy",
      "category_name": "מיתולוגיה ופנטזיה",
      "answer": "פניקס",
      "answer_niqqud": "פֶנִיקְס",
      "clues": [
        "אֲנִי מֵעוֹלָם דִּמְיוֹנִי אוֹ מִיתוֹלוֹגִי",
        "אֲנִי עוֹף אַגָּדִי שֶׁקָּשׁוּר לְאֵשׁ וּלְהִתְחַדְּשׁוּת",
        "לְעִתִּים אֲנִי נִשְׂרָף וְנוֹלָד שׁוּב מִן הָאֵפֶר",
        "הַנּוֹצוֹת שֶׁלִּי מְתֹאָרוֹת כְּאָדֻמּוֹת וּזְהֻבּוֹת",
        "אֲנִי מְסַמֵּל תִּקְוָה אַחֲרֵי סוֹף קָשֶׁה",
        "הַחַיִּים שֶׁלִּי נִמְשָׁכִים בְּמַחְזוֹרִים מוּפְלָאִים",
        "בְּסִפּוּרִים אֲנִי נָדִיר וּמְלֵא הוֹד",
        "הַדְּמָעוֹת שֶׁלִּי מְרַפְּאוֹת לְעִתִּים בְּאַגָּדוֹת",
        "אֲנִי עוֹלֶה מִתּוֹךְ אֵפֶר כְּסִימָן לְהַתְחָלָה חֲדָשָׁה",
        "זֶה עוֹף מִיתוֹלוֹגִי שֶׁנוֹלָד מֵחָדָשׁ מִתּוֹךְ אֵפֶר"
      ],
      "grid": [
        "פניקס",
        "הידרה",
        "גריפין",
        "מדוזה",
        "קיקלופ",
        "ספינקס",
        "מינוטאור",
        "פגסוס",
        "קנטאור",
        "קרברוס",
        "בת ים",
        "קרקן",
        "אלף",
        "בזיליסק",
        "אורק",
        "גולם",
        "גובלין",
        "ערפד",
        "טרול",
        "איש זאב",
        "ענק",
        "מומיה",
        "גמד",
        "זומבי",
        "שדון",
        "שלד חי",
        "קוסם",
        "רוח רפאים",
        "מכשפה",
        "מלאך",
        "פיה",
        "שטן"
      ]
    },
    {
      "id": "mythology_fantasy_019",
      "category_id": "mythology_fantasy",
      "category_name": "מיתולוגיה ופנטזיה",
      "answer": "הידרה",
      "answer_niqqud": "הִידְרָה",
      "clues": [
        "אֲנִי מֵעוֹלָם דִּמְיוֹנִי אוֹ מִיתוֹלוֹגִי",
        "אֲנִי מִפְלֶצֶת מַיִם עַתִּיקָה וּמְסֻכֶּנֶת",
        "יֵשׁ לִי רָאשִׁים רַבִּים בְּסִפּוּר הַמֻּכָּר",
        "כְּשֶׁפּוֹגְעִים בְּחֵלֶק מִמֶּנִּי הַבְּעָיָה עֲלוּלָה לִגְדֹּל",
        "גִּבּוֹר מִיתוֹלוֹגִי הָיָה צָרִיךְ לְחַסֵּל אוֹתִי",
        "אֲנִי מְסַמֶּלֶת אֹיֵב שֶׁקָּשֶׁה לְהַכְרִיעַ",
        "בִּצּוֹת וּמְקוֹמוֹת לַחִים קְשׁוּרִים אֵלַי",
        "הַנְּשִׁימָה אוֹ הָאֶרֶס שֶׁלִּי מְסֻכָּנִים לְעִתִּים",
        "הַרְבֵּה צַוָּארִים מִתְנַפְּלִים מִמֶּנִּי בּבת אַחַת",
        "זֶה מִפְלֶצֶת מִיתוֹלוֹגִית בַּעֲלַת רָאשִׁים רַבִּים"
      ],
      "grid": [
        "הידרה",
        "מדוזה",
        "פניקס",
        "ספינקס",
        "גריפין",
        "פגסוס",
        "קיקלופ",
        "קרברוס",
        "מינוטאור",
        "קרקן",
        "קנטאור",
        "בזיליסק",
        "בת ים",
        "גולם",
        "אלף",
        "ערפד",
        "אורק",
        "איש זאב",
        "גובלין",
        "מומיה",
        "טרול",
        "זומבי",
        "ענק",
        "שלד חי",
        "גמד",
        "רוח רפאים",
        "שדון",
        "מלאך",
        "קוסם",
        "שטן",
        "מכשפה",
        "אל יווני"
      ]
    },
    {
      "id": "mythology_fantasy_020",
      "category_id": "mythology_fantasy",
      "category_name": "מיתולוגיה ופנטזיה",
      "answer": "מדוזה",
      "answer_niqqud": "מֶדוּזָה",
      "clues": [
        "אֲנִי מֵעוֹלָם דִּמְיוֹנִי אוֹ מִיתוֹלוֹגִי",
        "אֲנִי דְּמוּת מְסֻכֶּנֶת מִסִּפּוּר עַתִּיק",
        "הַשֵּׂעָר שֶׁלִּי מְתֹאָר כְּיְצוּרִים מִתְפַּתְּלִים",
        "מַבָּט יָשִׁיר בִּי עָלוּל לְהַקְפִּיא לְצוּרָה קָשָׁה",
        "גִּבּוֹר נֶעֱזַר בְּמָגֵן מַבְרִיק כְּדֵי לְהִתְמוֹדֵד אִתִּי",
        "הַפָּנִים שֶׁלִּי מְשַׁלְּבוֹת יֹפִי וְאֵימָה",
        "אֲנָשִׁים בַּסִּפּוּר נִזְהָרִים שֶׁלֹּא לְהַבִּיט בִּי",
        "אֲנִי מְסַמֶּלֶת כֹּחַ מְשַׁתֵּק וּמַבָּט מְסֻכָּן",
        "הָרֹאשׁ שֶׁלִּי הָפַךְ לְסִימָן מְפֻרְסָם",
        "זֶה דְּמוּת מִיתוֹלוֹגִית שֶׁשְּׂעָרָהּ נְחָשִׁים וּמַבָּטָהּ מְאַבֵּן"
      ],
      "grid": [
        "מדוזה",
        "ספינקס",
        "הידרה",
        "פגסוס",
        "פניקס",
        "קרברוס",
        "גריפין",
        "קרקן",
        "קיקלופ",
        "בזיליסק",
        "מינוטאור",
        "גולם",
        "קנטאור",
        "ערפד",
        "בת ים",
        "איש זאב",
        "אלף",
        "מומיה",
        "אורק",
        "זומבי",
        "גובלין",
        "שלד חי",
        "טרול",
        "רוח רפאים",
        "ענק",
        "מלאך",
        "גמד",
        "שטן",
        "שדון",
        "אל יווני",
        "קוסם",
        "אלה יוונית"
      ]
    },
    {
      "id": "mythology_fantasy_021",
      "category_id": "mythology_fantasy",
      "category_name": "מיתולוגיה ופנטזיה",
      "answer": "ספינקס",
      "answer_niqqud": "סְפִינְקְס",
      "clues": [
        "אֲנִי מֵעוֹלָם דִּמְיוֹנִי אוֹ מִיתוֹלוֹגִי",
        "אֲנִי יְצוּר מִיתוֹלוֹגִי שֶׁאוֹהֵב חִידוֹת",
        "הַגּוּף שֶׁלִּי מְשַׁלֵּב חַיָּה וּפָנִים דְּמוּיוֹת אָדָם",
        "לְעִתִּים אֲנִי שׁוֹמֵר עַל שַׁעַר אוֹ דֶּרֶךְ",
        "מִי שֶׁאֵינוֹ עוֹנֶה לִי נִמְצָא בְּסַכָּנָה בַּסִּפּוּר",
        "אֲנִי מְסַמֵּל חָכְמָה מִסְתּוֹרִין וְשְׁמִירָה",
        "בְּמִצְרַיִם הָעַתִּיקָה יֵשׁ דְּמוּת אֶבֶן עֲנָקִית שֶׁמַּזְכִּירָה אוֹתִי",
        "הַשְּׁאֵלָה שֶׁלִּי מַצְרִיכָה חָכְמָה וְזְהִירוּת",
        "אֲנִי שׁוֹכֵב לְעִתִּים כְּשׁוֹמֵר דּוֹמֵם בַּדִּמְיוֹן",
        "זֶה שׁוֹמֵר מִיתוֹלוֹגִי עִם גּוּף חַיָּה וְחִידָה קָטְלָנִית"
      ],
      "grid": [
        "ספינקס",
        "פגסוס",
        "מדוזה",
        "קרברוס",
        "הידרה",
        "קרקן",
        "פניקס",
        "בזיליסק",
        "גריפין",
        "גולם",
        "קיקלופ",
        "ערפד",
        "מינוטאור",
        "איש זאב",
        "קנטאור",
        "מומיה",
        "בת ים",
        "זומבי",
        "אלף",
        "שלד חי",
        "אורק",
        "רוח רפאים",
        "גובלין",
        "מלאך",
        "טרול",
        "שטן",
        "ענק",
        "אל יווני",
        "גמד",
        "אלה יוונית",
        "שדון",
        "ויקינג"
      ]
    },
    {
      "id": "mythology_fantasy_022",
      "category_id": "mythology_fantasy",
      "category_name": "מיתולוגיה ופנטזיה",
      "answer": "פגסוס",
      "answer_niqqud": "פֶּגַסוּס",
      "clues": [
        "אֲנִי מֵעוֹלָם דִּמְיוֹנִי אוֹ מִיתוֹלוֹגִי",
        "אֲנִי יְצוּר עָדִין שֶׁדּוֹמֶה לְסוּס מֻפְלָא",
        "יֵשׁ לִי כְּנָפַיִם גְּדוֹלוֹת",
        "אֲנִי מְסֻגָּל לְהַמְרִיא מֵעַל הֶעָנָנִים",
        "בְּסִפּוּרִים עַתִּיקִים אֲנִי קָשׁוּר לְגִבּוֹרִים וּלְהַשְׁרָאָה",
        "הַמַּרְאֶה שֶׁלִּי לָבָן וּמְהֻדָּר לְעִתִּים",
        "אֲנִי מְחַבֵּר בֵּין רְכִיבָה לְתְעוּפָה",
        "לְעִתִּים אֲנִי מוֹפִיעַ בְּסֵמֶל שֶׁל דִּמְיוֹן וְחֵרוּת",
        "הַפַּרְסוֹת שֶׁלִּי נוֹגְעוֹת בַּקַּרְקַע וְהַכְּנָפַיִם בַּשָּׁמַיִם",
        "זֶה סוּס מִיתוֹלוֹגִי בַּעַל כְּנָפַיִם"
      ],
      "grid": [
        "פגסוס",
        "קרברוס",
        "ספינקס",
        "קרקן",
        "מדוזה",
        "בזיליסק",
        "הידרה",
        "גולם",
        "פניקס",
        "ערפד",
        "גריפין",
        "איש זאב",
        "קיקלופ",
        "מומיה",
        "מינוטאור",
        "זומבי",
        "קנטאור",
        "שלד חי",
        "בת ים",
        "רוח רפאים",
        "אלף",
        "מלאך",
        "אורק",
        "שטן",
        "גובלין",
        "אל יווני",
        "טרול",
        "אלה יוונית",
        "ענק",
        "ויקינג",
        "גמד",
        "אביר"
      ]
    },
    {
      "id": "mythology_fantasy_023",
      "category_id": "mythology_fantasy",
      "category_name": "מיתולוגיה ופנטזיה",
      "answer": "קרברוס",
      "answer_niqqud": "קֶרְבֵּרוֹס",
      "clues": [
        "אֲנִי מֵעוֹלָם דִּמְיוֹנִי אוֹ מִיתוֹלוֹגִי",
        "אֲנִי שׁוֹמֵר מַפְחִיד מִן הָעוֹלָם הָעַתִּיק",
        "יֵשׁ לִי כַּמָּה רָאשִׁים שֶׁנּוֹהֲמִים בְּיַחַד",
        "אֲנִי שׁוֹמֵר עַל כְּנִיסָה לְמָקוֹם אֲפֵל בְּסִפּוּרִים",
        "הַגּוּף שֶׁלִּי דּוֹמֶה לְכֶלֶב עָצוּם וּמְסֻכָּן",
        "אֲנִי מוֹנֵעַ מֵרְשָׁעִים אוֹ מִנְּשָׁמוֹת לַעֲבֹר לְעִתִּים",
        "גִּבּוֹר חָזָק הָיָה צָרִיךְ לְהִתְמוֹדֵד אִתִּי",
        "הַשְּׁמִירָה שֶׁלִּי כִּמְעַט בִּלְתִּי אֶפְשָׁרִית לְעֲקִיפָה",
        "אֲנִי מְסַמֵּל סַף בֵּין עוֹלָמוֹת",
        "זֶה כֶּלֶב מִיתוֹלוֹגִי עָצוּם עִם שְׁלוֹשָׁה רָאשִׁים"
      ],
      "grid": [
        "קרברוס",
        "קרקן",
        "פגסוס",
        "בזיליסק",
        "ספינקס",
        "גולם",
        "מדוזה",
        "ערפד",
        "הידרה",
        "איש זאב",
        "פניקס",
        "מומיה",
        "גריפין",
        "זומבי",
        "קיקלופ",
        "שלד חי",
        "מינוטאור",
        "רוח רפאים",
        "קנטאור",
        "מלאך",
        "בת ים",
        "שטן",
        "אלף",
        "אל יווני",
        "אורק",
        "אלה יוונית",
        "גובלין",
        "ויקינג",
        "טרול",
        "אביר",
        "ענק",
        "נסיך"
      ]
    },
    {
      "id": "mythology_fantasy_024",
      "category_id": "mythology_fantasy",
      "category_name": "מיתולוגיה ופנטזיה",
      "answer": "קרקן",
      "answer_niqqud": "קְרָקֶן",
      "clues": [
        "אֲנִי מֵעוֹלָם דִּמְיוֹנִי אוֹ מִיתוֹלוֹגִי",
        "אֲנִי מִפְלֶצֶת יַמִּית עֲנָקִית",
        "לְעִתִּים אֲנִי גָּר בְּמַעֲמַקִּים שֶׁאֵין רוֹאִים",
        "הַזְּרוֹעוֹת שֶׁלִּי עֲצוּמוֹת וּמִתְפַּתְּלוֹת",
        "מַלָּחִים מְסַפְּרִים עָלַי בְּפַחַד",
        "אֳנִיָּה שֶׁפּוֹגֶשֶׁת אוֹתִי עֲלוּלָה לְהֵעָלֵם",
        "אֲנִי מְסַמֵּל אֶת הַפַּחַד מִמַּה שֶּׁמִּתַּחַת לַמַּיִם",
        "לְעִתִּים רוֹאִים רַק חֵלֶק קָטָן מִמֶּנִּי עוֹלֶה מִן הַמַּיִם",
        "הַיָּם נִרְאֶה שָׁקֵט עַד שֶׁאֲנִי מוֹפִיעַ",
        "זֶה מִפְלֶצֶת עֲנָקִית מֵהַיָּם עִם זְרוֹעוֹת רַבּוֹת"
      ],
      "grid": [
        "קרקן",
        "בזיליסק",
        "קרברוס",
        "גולם",
        "פגסוס",
        "ערפד",
        "ספינקס",
        "איש זאב",
        "מדוזה",
        "מומיה",
        "הידרה",
        "זומבי",
        "פניקס",
        "שלד חי",
        "גריפין",
        "רוח רפאים",
        "קיקלופ",
        "מלאך",
        "מינוטאור",
        "שטן",
        "קנטאור",
        "אל יווני",
        "בת ים",
        "אלה יוונית",
        "אלף",
        "ויקינג",
        "אורק",
        "אביר",
        "גובלין",
        "נסיך",
        "טרול",
        "נסיכה"
      ]
    },
    {
      "id": "mythology_fantasy_025",
      "category_id": "mythology_fantasy",
      "category_name": "מיתולוגיה ופנטזיה",
      "answer": "בזיליסק",
      "answer_niqqud": "בָּזִילִיסְק",
      "clues": [
        "אֲנִי מֵעוֹלָם דִּמְיוֹנִי אוֹ מִיתוֹלוֹגִי",
        "אֲנִי יְצוּר קָטְלָנִי מֵאַגָּדוֹת אֵירוֹפָּאִיּוֹת",
        "הַמַּבָּט שֶׁלִּי נֶחְשָׁב מְסֻכָּן מְאֹד",
        "לְעִתִּים אֲנִי מְתֹאָר כְּשִׁלּוּב שֶׁל זוֹחֵל וְעוֹף",
        "אֲנִי מְכֻנֶּה לְעִתִּים שַׁלִּיט שֶׁל יְצוּרִים זוֹחֲלִים",
        "אֶרֶס וְאֵימָה קְשׁוּרִים אֵלַי",
        "בְּסִפּוּרִים מְסֻיָּמִים אֲפִלּוּ הִסְתַּכְּלוּת יְכוֹלָה לְהָרֹג",
        "הַגֹּדֶל שֶׁלִּי לֹא תָּמִיד עָצוּם אֲבָל הַסַּכָּנָה גְּדוֹלָה",
        "אֲנִי מִסְתַּתֵּר בְּמְקוֹמוֹת חֲשׁוּכִים בְּדִמְיוֹן",
        "זֶה יְצוּר מַפְחִיד שֶׁמַּבָּטוֹ יָכוֹל לְהָבִיא אָסוֹן"
      ],
      "grid": [
        "בזיליסק",
        "גולם",
        "קרקן",
        "ערפד",
        "קרברוס",
        "איש זאב",
        "פגסוס",
        "מומיה",
        "ספינקס",
        "זומבי",
        "מדוזה",
        "שלד חי",
        "הידרה",
        "רוח רפאים",
        "פניקס",
        "מלאך",
        "גריפין",
        "שטן",
        "קיקלופ",
        "אל יווני",
        "מינוטאור",
        "אלה יוונית",
        "קנטאור",
        "ויקינג",
        "בת ים",
        "אביר",
        "אלף",
        "נסיך",
        "אורק",
        "נסיכה",
        "גובלין",
        "מלך"
      ]
    },
    {
      "id": "mythology_fantasy_026",
      "category_id": "mythology_fantasy",
      "category_name": "מיתולוגיה ופנטזיה",
      "answer": "גולם",
      "answer_niqqud": "גֹּלֶם",
      "clues": [
        "אֲנִי מֵעוֹלָם דִּמְיוֹנִי אוֹ מִיתוֹלוֹגִי",
        "אֲנִי דְּמוּת שֶׁנּוֹצְרָה מֵחֹמֶר דּוֹמֵם",
        "לְעִתִּים אֲנִי עָשׂוּי מֵחֵמָר אוֹ מֵאֲדָמָה",
        "אֲנִי מְצַיֵּת לְמִי שֶׁהֵעִיר אוֹתִי לְחַיִּים",
        "בְּאַגָּדָה יְהוּדִית מְפֻרְסֶמֶת אֲנִי שׁוֹמֵר עַל קְהִלָּה",
        "אֲנִי חָזָק וְשָׁקֵט לְעִתִּים",
        "הַחַיִּים שֶׁלִּי מַגִּיעִים מִמִּלָּה אוֹ מֵסוֹד",
        "אֲנִי מְסַמֵּל כֹּחַ שֶׁנִּבְרָא בִּידֵי אָדָם",
        "לְעִתִּים הַשְּׁלִיטָה בִּי יְכוֹלָה לְהִסְתַּבֵּךְ",
        "זֶה דְּמוּת חֵמָר שֶׁקִּבְּלָה חַיִּים בְּכֹחַ נִסְתָּר"
      ],
      "grid": [
        "גולם",
        "ערפד",
        "בזיליסק",
        "איש זאב",
        "קרקן",
        "מומיה",
        "קרברוס",
        "זומבי",
        "פגסוס",
        "שלד חי",
        "ספינקס",
        "רוח רפאים",
        "מדוזה",
        "מלאך",
        "הידרה",
        "שטן",
        "פניקס",
        "אל יווני",
        "גריפין",
        "אלה יוונית",
        "קיקלופ",
        "ויקינג",
        "מינוטאור",
        "אביר",
        "קנטאור",
        "נסיך",
        "בת ים",
        "נסיכה",
        "אלף",
        "מלך",
        "אורק",
        "מלכה"
      ]
    },
    {
      "id": "mythology_fantasy_027",
      "category_id": "mythology_fantasy",
      "category_name": "מיתולוגיה ופנטזיה",
      "answer": "ערפד",
      "answer_niqqud": "עַרְפָּד",
      "clues": [
        "אֲנִי מֵעוֹלָם דִּמְיוֹנִי אוֹ מִיתוֹלוֹגִי",
        "אֲנִי דְּמוּת לֵילִית מְפֻרְסֶמֶת וּמְפַחִידָה",
        "לְעִתִּים אֲנִי גָּר בְּטִירָה אֲפֵלָה",
        "אוֹר הַיּוֹם מְסֻכָּן לִי בְּסִפּוּרִים רַבִּים",
        "הַשִּׁנַּיִם שֶׁלִּי חַדּוֹת וּבוֹלְטוֹת",
        "אֲנִי קָשׁוּר לְעַטְלַפִּים וּלְגְלִימָה שְׁחֹרָה לְעִתִּים",
        "אֵין לִי הִשְׁתַּקְּפוּת בְּמַרְאָה בְּחֵלֶק מֵהָאַגָּדוֹת",
        "אֲנִי מְחַפֵּשׂ קָרְבָּנוֹת בַּלַּיְלָה",
        "שׁוּם וְיָתֵד עֵץ קְשׁוּרִים לְדַרְכֵי הֲגָנָה מִמֶּנִּי",
        "זֶה יְצוּר לַיְלָה שֶׁמְּפַחֵד מֵאוֹר וּמְזֹהֶה עִם נִיבִים חַדִּים"
      ],
      "grid": [
        "ערפד",
        "איש זאב",
        "גולם",
        "מומיה",
        "בזיליסק",
        "זומבי",
        "קרקן",
        "שלד חי",
        "קרברוס",
        "רוח רפאים",
        "פגסוס",
        "מלאך",
        "ספינקס",
        "שטן",
        "מדוזה",
        "אל יווני",
        "הידרה",
        "אלה יוונית",
        "פניקס",
        "ויקינג",
        "גריפין",
        "אביר",
        "קיקלופ",
        "נסיך",
        "מינוטאור",
        "נסיכה",
        "קנטאור",
        "מלך",
        "בת ים",
        "מלכה",
        "אלף",
        "חרב קסומה"
      ]
    },
    {
      "id": "mythology_fantasy_028",
      "category_id": "mythology_fantasy",
      "category_name": "מיתולוגיה ופנטזיה",
      "answer": "איש זאב",
      "answer_niqqud": "אִישׁ זְאֵב",
      "clues": [
        "אֲנִי מֵעוֹלָם דִּמְיוֹנִי אוֹ מִיתוֹלוֹגִי",
        "אֲנִי אָדָם שֶׁמִּשְׁתַּנֶּה לְטוֹרֵף בְּסִפּוּרִים",
        "הַשִּׁנּוּי שֶׁלִּי קָשׁוּר לְלַיְלָה מְיֻחָד וְעָגֹל בַּשָּׁמַיִם",
        "בִּצּוּרָה הַשְּׁנִיָּה שֶׁלִּי יֵשׁ פַּרְוָה טְפָרִים וְשִׁנַּיִם",
        "אֲנִי מְסַמֵּל מַאֲבָק בֵּין אָדָם לְחַיָּה פְּנִימִית",
        "יְלָלָה בַּלַּיְלָה קְשׁוּרָה אֵלַי",
        "בְּסִפּוּרִים אֲנָשִׁים חוֹשְׁשִׁים מִמֶּנִּי בַּיַּעַר",
        "לְעִתִּים כֶּסֶף נֶחְשָׁב לְחֻלְשָׁה שֶׁלִּי",
        "בַּבֹּקֶר אֲנִי עָלוּל לְחַזֹּר לְמַרְאֶה רָגִיל",
        "זֶה אָדָם שֶׁבְּלֵיל יָרֵחַ מָלֵא הוֹפֵךְ לְטוֹרֵף מְיַלֵּל"
      ],
      "grid": [
        "איש זאב",
        "מומיה",
        "ערפד",
        "זומבי",
        "גולם",
        "שלד חי",
        "בזיליסק",
        "רוח רפאים",
        "קרקן",
        "מלאך",
        "קרברוס",
        "שטן",
        "פגסוס",
        "אל יווני",
        "ספינקס",
        "אלה יוונית",
        "מדוזה",
        "ויקינג",
        "הידרה",
        "אביר",
        "פניקס",
        "נסיך",
        "גריפין",
        "נסיכה",
        "קיקלופ",
        "מלך",
        "מינוטאור",
        "מלכה",
        "קנטאור",
        "חרב קסומה",
        "בת ים",
        "שרביט קסמים"
      ]
    },
    {
      "id": "mythology_fantasy_029",
      "category_id": "mythology_fantasy",
      "category_name": "מיתולוגיה ופנטזיה",
      "answer": "מומיה",
      "answer_niqqud": "מוּמְיָה",
      "clues": [
        "אֲנִי מֵעוֹלָם דִּמְיוֹנִי אוֹ מִיתוֹלוֹגִי",
        "אֲנִי דְּמוּת עַתִּיקָה שֶׁעֲטוּפָה בְּרְצוּעוֹת בַּד",
        "קְבָרִים וּפִירָמִידוֹת קְשׁוּרִים אֵלַי בַּדִּמְיוֹן",
        "לְעִתִּים אֲנִי מִתְעוֹרֶרֶת אַחֲרֵי שָׁנִים רַבּוֹת",
        "הַתְּנוּעָה שֶׁלִּי אִטִּית וּמְאיימֶת",
        "אֲנִי מְסַמֶּלֶת קְלָלָה מִן הֶעָבָר",
        "חול מִדְבָּרִי וְאוֹצָרוֹת קְבוּרִים מוֹפִיעִים לְיָדִי לְעִתִּים",
        "הַפָּנִים שֶׁלִּי מֻסְתָּרוֹת בְּשִׁכְבוֹת",
        "אֲנִי מוֹפִיעָה הַרְבֵּה בְּסִפּוּרֵי אֵימָה קַלִּים",
        "זֶה גּוּפָה עַתִּיקָה עֲטוּפָה בְּתַחְבּוֹשׁוֹת שֶׁקָּמָה לַחַיִּים"
      ],
      "grid": [
        "מומיה",
        "זומבי",
        "איש זאב",
        "שלד חי",
        "ערפד",
        "רוח רפאים",
        "גולם",
        "מלאך",
        "בזיליסק",
        "שטן",
        "קרקן",
        "אל יווני",
        "קרברוס",
        "אלה יוונית",
        "פגסוס",
        "ויקינג",
        "ספינקס",
        "אביר",
        "מדוזה",
        "נסיך",
        "הידרה",
        "נסיכה",
        "פניקס",
        "מלך",
        "גריפין",
        "מלכה",
        "קיקלופ",
        "חרב קסומה",
        "מינוטאור",
        "שרביט קסמים",
        "קנטאור",
        "טבעת קסומה"
      ]
    },
    {
      "id": "mythology_fantasy_030",
      "category_id": "mythology_fantasy",
      "category_name": "מיתולוגיה ופנטזיה",
      "answer": "זומבי",
      "answer_niqqud": "זוֹמְבִּי",
      "clues": [
        "אֲנִי מֵעוֹלָם דִּמְיוֹנִי אוֹ מִיתוֹלוֹגִי",
        "אֲנִי דְּמוּת אֵימָה שֶׁנָּעָה לְלֹא מַחֲשָׁבָה רַבָּה",
        "לְעִתִּים אֲנִי מוֹפִיעַ בַּהֲמוֹן גָּדוֹל וּמְאיים",
        "הַהֲלִיכָה שֶׁלִּי אִטִּית וּמֻזָּרָה לְעִתִּים",
        "בְּסִפּוּרִים רַבִּים אֲנִי מְסַמֵּל עוֹלָם שֶׁהִשְׁתַּבֵּשׁ",
        "אֲנָשִׁים מִתְחַבְּאִים מִמֶּנִּי בְּעִיר רֵיקָה",
        "אֲנִי מְחַפֵּשׂ קָרְבָּנוֹת בְּלִי לַעֲצֹר",
        "הַמַּרְאֶה שֶׁלִּי מְרֻשָּׁל וּמְפַחִיד",
        "לְעִתִּים נְשִׁיכָה מִמֶּנִּי מַדְבִּיקָה אֲחֵרִים בַּסִּפּוּר",
        "זֶה דְּמוּת אֵימָה מְהַלֶּכֶת שֶׁנִּרְאֵית כְּמֵת שֶׁקָּם"
      ],
      "grid": [
        "זומבי",
        "שלד חי",
        "מומיה",
        "רוח רפאים",
        "איש זאב",
        "מלאך",
        "ערפד",
        "שטן",
        "גולם",
        "אל יווני",
        "בזיליסק",
        "אלה יוונית",
        "קרקן",
        "ויקינג",
        "קרברוס",
        "אביר",
        "פגסוס",
        "נסיך",
        "ספינקס",
        "נסיכה",
        "מדוזה",
        "מלך",
        "הידרה",
        "מלכה",
        "פניקס",
        "חרב קסומה",
        "גריפין",
        "שרביט קסמים",
        "קיקלופ",
        "טבעת קסומה",
        "מינוטאור",
        "שיקוי קסמים"
      ]
    },
    {
      "id": "mythology_fantasy_031",
      "category_id": "mythology_fantasy",
      "category_name": "מיתולוגיה ופנטזיה",
      "answer": "שלד חי",
      "answer_niqqud": "שֶׁלֶד חַי",
      "clues": [
        "אֲנִי מֵעוֹלָם דִּמְיוֹנִי אוֹ מִיתוֹלוֹגִי",
        "אֲנִי דְּמוּת אֵימָה שֶׁנִּשְׁאֲרוּ מִמֶּנָּה בְּעִקָּר עֲצָמוֹת",
        "אֲנִי מִתְהַלֵּךְ בְּלִי בָּשָׂר בַּדִּמְיוֹן",
        "רַעַשׁ קִרְקוּשׁ יָכוֹל לְלַוּוֹת אֶת צְעָדַי",
        "לְעִתִּים אֲנִי שׁוֹמֵר עַל מְעָרָה אוֹ קְבָר",
        "חֶרֶב חֲלוּדָה וּמָגֵן שָׁבוּר קְשׁוּרִים אֵלַי לְעִתִּים",
        "אֲנִי מְסַמֵּל מָוֶת שֶׁקִּבֵּל תְּנוּעָה",
        "בְּמִשְׂחָקֵי פַנְטָזְיָה אֲנִי אוֹיֵב קְלַאסִי",
        "הָעֵינַיִם שֶׁלִּי רֵיקוֹת אֲבָל מְפַחִידוֹת",
        "זֶה גּוּף עֲצָמוֹת שֶׁמִּתְהַלֵּךְ כְּאִלּוּ הוּא בַּחַיִּים"
      ],
      "grid": [
        "שלד חי",
        "רוח רפאים",
        "זומבי",
        "מלאך",
        "מומיה",
        "שטן",
        "איש זאב",
        "אל יווני",
        "ערפד",
        "אלה יוונית",
        "גולם",
        "ויקינג",
        "בזיליסק",
        "אביר",
        "קרקן",
        "נסיך",
        "קרברוס",
        "נסיכה",
        "פגסוס",
        "מלך",
        "ספינקס",
        "מלכה",
        "מדוזה",
        "חרב קסומה",
        "הידרה",
        "שרביט קסמים",
        "פניקס",
        "טבעת קסומה",
        "גריפין",
        "שיקוי קסמים",
        "קיקלופ",
        "ספר לחשים"
      ]
    },
    {
      "id": "mythology_fantasy_032",
      "category_id": "mythology_fantasy",
      "category_name": "מיתולוגיה ופנטזיה",
      "answer": "רוח רפאים",
      "answer_niqqud": "רוּחַ רְפָאִים",
      "clues": [
        "אֲנִי מֵעוֹלָם דִּמְיוֹנִי אוֹ מִיתוֹלוֹגִי",
        "אֲנִי דְּמוּת שְׁקוּפָה שֶׁנִּשְׁאֶרֶת אַחֲרֵי הַחַיִּים בַּסִּפּוּר",
        "לְעִתִּים אֲנִי מְרַחֶפֶת בְּמָקוֹם יָשָׁן וַחֲשׁוּךְ",
        "הַקּוֹל שֶׁלִּי יָכוֹל לִהְיוֹת לְחִישָׁה קְרִירָה",
        "אֲנִי עָלוּלָה לְהַפְחִיד מִי שֶׁנִּכְנָס לְבַיִת נָטוּשׁ",
        "לְעִתִּים אֵינִי יְכוֹלָה לָגַעַת בְּחֲפָצִים",
        "אֲנִי מְסַמֶּלֶת סוֹד שֶׁלֹא נִפְתַּר",
        "מַרְאֶה לָבָן וְעָרְפִלִּי קְשׁוּר אֵלַי",
        "אֲנִי מוֹפִיעָה בְּסִפּוּרֵי רְדִיפָה וְטִירוֹת יְשָׁנוֹת",
        "זֶה דְּמוּת שְׁקוּפָה שֶׁמְּרַחֶפֶת וּמַפְחִידָה בְּלַיְלָה"
      ],
      "grid": [
        "רוח רפאים",
        "מלאך",
        "שלד חי",
        "שטן",
        "זומבי",
        "אל יווני",
        "מומיה",
        "אלה יוונית",
        "איש זאב",
        "ויקינג",
        "ערפד",
        "אביר",
        "גולם",
        "נסיך",
        "בזיליסק",
        "נסיכה",
        "קרקן",
        "מלך",
        "קרברוס",
        "מלכה",
        "פגסוס",
        "חרב קסומה",
        "ספינקס",
        "שרביט קסמים",
        "מדוזה",
        "טבעת קסומה",
        "הידרה",
        "שיקוי קסמים",
        "פניקס",
        "ספר לחשים",
        "גריפין",
        "שער קסום"
      ]
    },
    {
      "id": "mythology_fantasy_033",
      "category_id": "mythology_fantasy",
      "category_name": "מיתולוגיה ופנטזיה",
      "answer": "מלאך",
      "answer_niqqud": "מַלְאָךְ",
      "clues": [
        "אֲנִי מֵעוֹלָם דִּמְיוֹנִי אוֹ מִיתוֹלוֹגִי",
        "אֲנִי דְּמוּת שְׁמֵימִית שֶׁמְּסַמֶּלֶת טוֹב לֵב וּשְׁלִיחוּת",
        "לְעִתִּים מְצַיְּרִים אוֹתִי עִם כְּנָפַיִם לְבָנוֹת",
        "הִלָּה שֶׁל אוֹר מוֹפִיעָה מֵעָלַי לְעִתִּים",
        "אֲנִי מֵבִיא בְּשׂוֹרָה אוֹ שְׁמִירָה בְּסִפּוּרִים רַבִּים",
        "הַמַּרְאֶה שֶׁלִּי נֶחְשָׁב טָהוֹר וְשָׁקֵט",
        "אֲנִי קָשׁוּר לְעוֹלָמוֹת עֶלְיוֹנִים וּלְאוֹר",
        "בְּתַרְבּוּיוֹת רַבּוֹת אֲנִי נֶחְשָׁב שָׁלִיחַ שֶׁל כֹּחַ גָּבוֹהַּ",
        "לְעִתִּים אֲנִי שׁוֹמֵר עַל אָדָם מִבְּלִי שֶׁיִּרְאוּ אוֹתִי",
        "זֶה דְּמוּת שְׁמֵימִית עִם כְּנָפַיִם וְהִלָּה"
      ],
      "grid": [
        "מלאך",
        "שטן",
        "רוח רפאים",
        "אל יווני",
        "שלד חי",
        "אלה יוונית",
        "זומבי",
        "ויקינג",
        "מומיה",
        "אביר",
        "איש זאב",
        "נסיך",
        "ערפד",
        "נסיכה",
        "גולם",
        "מלך",
        "בזיליסק",
        "מלכה",
        "קרקן",
        "חרב קסומה",
        "קרברוס",
        "שרביט קסמים",
        "פגסוס",
        "טבעת קסומה",
        "ספינקס",
        "שיקוי קסמים",
        "מדוזה",
        "ספר לחשים",
        "הידרה",
        "שער קסום",
        "פניקס",
        "מבוך"
      ]
    },
    {
      "id": "mythology_fantasy_034",
      "category_id": "mythology_fantasy",
      "category_name": "מיתולוגיה ופנטזיה",
      "answer": "שטן",
      "answer_niqqud": "שָׂטָן",
      "clues": [
        "אֲנִי מֵעוֹלָם דִּמְיוֹנִי אוֹ מִיתוֹלוֹגִי",
        "אֲנִי דְּמוּת שֶׁמְּסַמֶּלֶת רֹעַ וּפִתּוּי בְּסִפּוּרִים רַבִּים",
        "לְעִתִּים מְצַיְּרִים אוֹתִי עִם קְרָנַיִם וְזָנָב",
        "צֶבַע אָדֹם וְאֵשׁ קְשׁוּרִים אֵלַי בַּדִּמְיוֹן",
        "אֲנִי מוֹפִיעַ כְּנוֹסֵא עִסְקָאוֹת מְסֻכָּנוֹת לְעִתִּים",
        "בְּסִפּוּרִים אֲנִי מְנַסֶּה לְהַטְעוֹת בְּנֵי אָדָם",
        "אֲנִי מְסַמֵּל מַאֲבָק מוּסָרִי וּפַחַד עָמֹק",
        "לְעִתִּים הַמַּרְאֶה שֶׁלִּי מְפֹאָר אֲבָל מְאיים",
        "מְקוֹם חַם וַאֲפֵל קָשׁוּר אֵלַי בְּמַסּוֹרוֹת רַבּוֹת",
        "זֶה דְּמוּת רָעָה בַּעֲלַת קְרָנַיִם שֶׁמְּפַתָּה בְּסִפּוּרִים"
      ],
      "grid": [
        "שטן",
        "אל יווני",
        "מלאך",
        "אלה יוונית",
        "רוח רפאים",
        "ויקינג",
        "שלד חי",
        "אביר",
        "זומבי",
        "נסיך",
        "מומיה",
        "נסיכה",
        "איש זאב",
        "מלך",
        "ערפד",
        "מלכה",
        "גולם",
        "חרב קסומה",
        "בזיליסק",
        "שרביט קסמים",
        "קרקן",
        "טבעת קסומה",
        "קרברוס",
        "שיקוי קסמים",
        "פגסוס",
        "ספר לחשים",
        "ספינקס",
        "שער קסום",
        "מדוזה",
        "מבוך",
        "הידרה",
        "אוצר מקולל"
      ]
    },
    {
      "id": "mythology_fantasy_035",
      "category_id": "mythology_fantasy",
      "category_name": "מיתולוגיה ופנטזיה",
      "answer": "אל יווני",
      "answer_niqqud": "אֵל יְוָנִי",
      "clues": [
        "אֲנִי מֵעוֹלָם דִּמְיוֹנִי אוֹ מִיתוֹלוֹגִי",
        "אֲנִי דְּמוּת עֶלְיוֹנָה מֵאַמּוּנוֹת עַתִּיקוֹת",
        "לְעִתִּים אֲנִי שׁוֹכֵן עַל הַר גָּבוֹהַּ בַּסִּפּוּרִים",
        "אֲנִי שׁוֹלֵט בְּתְחוּם כְּמוֹ יָם שָׁמַיִם אוֹ מִלְחָמָה",
        "בְּאַגָּדוֹת עַתִּיקוֹת אֲנִי מִתְעָרֵב בְּחַיֵּי בְּנֵי אָדָם",
        "לְעִתִּים יֵשׁ לִי סֵמֶל כְּמוֹ בָּרָק קִלְשׁוֹן אוֹ קַסְדָּה",
        "אֲנִי מְסַמֵּל כֹּחַ עָצוּם וְאֹפִי אֱנוֹשִׁי לְעִתִּים",
        "מִקְדָּשִׁים וּפֶסֶל שַׁיִשׁ קְשׁוּרִים אֵלַי",
        "הַסִּפּוּרִים עָלַי עֲדַיִן מֻכָּרִים בְּתַרְבּוּת מוֹדֶרְנִית",
        "זֶה כֹּחַ עֶלְיוֹן מֵהַמִּיתוֹלוֹגְיָה שֶׁל אָתֵנָה וְאוֹלִימְפּוּס"
      ],
      "grid": [
        "אל יווני",
        "אלה יוונית",
        "שטן",
        "ויקינג",
        "מלאך",
        "אביר",
        "רוח רפאים",
        "נסיך",
        "שלד חי",
        "נסיכה",
        "זומבי",
        "מלך",
        "מומיה",
        "מלכה",
        "איש זאב",
        "חרב קסומה",
        "ערפד",
        "שרביט קסמים",
        "גולם",
        "טבעת קסומה",
        "בזיליסק",
        "שיקוי קסמים",
        "קרקן",
        "ספר לחשים",
        "קרברוס",
        "שער קסום",
        "פגסוס",
        "מבוך",
        "ספינקס",
        "אוצר מקולל",
        "מדוזה",
        "דרקון"
      ]
    },
    {
      "id": "mythology_fantasy_036",
      "category_id": "mythology_fantasy",
      "category_name": "מיתולוגיה ופנטזיה",
      "answer": "אלה יוונית",
      "answer_niqqud": "אֵלָה יְוָנִית",
      "clues": [
        "אֲנִי מֵעוֹלָם דִּמְיוֹנִי אוֹ מִיתוֹלוֹגִי",
        "אֲנִי דְּמוּת נְקֵבָה עֶלְיוֹנָה מֵאַמּוּנוֹת עַתִּיקוֹת",
        "אֲנִי שׁוֹלֶטֶת בִּתְחוּם כְּמוֹ חָכְמָה אַהֲבָה אוֹ צַיִד",
        "לְעִתִּים מְלַוִּים אוֹתִי סְמָלִים כְּמוֹ יַנְשׁוּף קֶשֶׁת אוֹ יוֹנָה",
        "מִקְדָּשִׁים וּפְסָלִים עַתִּיקִים נִבְנוּ לִכְבוֹדִי",
        "בְּסִפּוּרִים אֲנִי יְכוֹלָה לַעֲזֹר אוֹ לְהַעֲנִישׁ בְּנֵי אָדָם",
        "אֲנִי מְשַׁלֶּבֶת יֹפִי כֹּחַ וְאֹפִי חָזָק",
        "הַסִּפּוּרִים עָלַי מְלֵאִים קִנְאָה חָכְמָה וְגַאֲוָה",
        "אֲנִי שַׁיֶּכֶת לְעוֹלָם שֶׁל אוֹלִימְפּוּס וְגִבּוֹרִים עַתִּיקִים",
        "זֶה כֹּחַ נָשִׁי עֶלְיוֹן מֵהַמִּיתוֹלוֹגְיָה הָעַתִּיקָה"
      ],
      "grid": [
        "אלה יוונית",
        "ויקינג",
        "אל יווני",
        "אביר",
        "שטן",
        "נסיך",
        "מלאך",
        "נסיכה",
        "רוח רפאים",
        "מלך",
        "שלד חי",
        "מלכה",
        "זומבי",
        "חרב קסומה",
        "מומיה",
        "שרביט קסמים",
        "איש זאב",
        "טבעת קסומה",
        "ערפד",
        "שיקוי קסמים",
        "גולם",
        "ספר לחשים",
        "בזיליסק",
        "שער קסום",
        "קרקן",
        "מבוך",
        "קרברוס",
        "אוצר מקולל",
        "פגסוס",
        "דרקון",
        "ספינקס",
        "חד קרן"
      ]
    },
    {
      "id": "mythology_fantasy_037",
      "category_id": "mythology_fantasy",
      "category_name": "מיתולוגיה ופנטזיה",
      "answer": "ויקינג",
      "answer_niqqud": "וִיקִינְג",
      "clues": [
        "אֲנִי מֵעוֹלָם דִּמְיוֹנִי אוֹ מִיתוֹלוֹגִי",
        "אֲנִי לוֹחֵם צְפוֹנִי מִסִּפּוּרִים וְהִיסְטוֹרְיָה",
        "סְפִינוֹת אֲרֻכּוֹת וְיַמִּים קָרִים קְשׁוּרִים אֵלַי",
        "לְעִתִּים מְצַיְּרִים אוֹתִי עִם קַסְדָּה גַּרְזֶן וְזָקָן",
        "אֲנִי מוֹפִיעַ בְּסִפּוּרִים עַל מַסָּעוֹת פְּשִׁיטוֹת וְאֵלִים צְפוֹנִיִּים",
        "הַבַּיִת שֶׁלִּי נִדְמֶה קָרוֹב לְפְיוֹרְדִים וְשֶׁלֶג",
        "אֲנִי מְסַמֵּל אֹמֶץ כֹּחַ וְחַיֵּי יָם",
        "שִׁירֵי קְרָב וְסִפּוּרֵי סַגָּה קְשׁוּרִים אֵלַי",
        "הַמַּרְאֶה שֶׁלִּי מְשַׁלֵּב פַּרְוָה מַתֶּכֶת וְנֶשֶׁק",
        "זֶה לוֹחֵם צְפוֹנִי עַתִּיק עִם סְפִינָה אֲרֻכָּה וְגַרְזֶן"
      ],
      "grid": [
        "ויקינג",
        "אביר",
        "אלה יוונית",
        "נסיך",
        "אל יווני",
        "נסיכה",
        "שטן",
        "מלך",
        "מלאך",
        "מלכה",
        "רוח רפאים",
        "חרב קסומה",
        "שלד חי",
        "שרביט קסמים",
        "זומבי",
        "טבעת קסומה",
        "מומיה",
        "שיקוי קסמים",
        "איש זאב",
        "ספר לחשים",
        "ערפד",
        "שער קסום",
        "גולם",
        "מבוך",
        "בזיליסק",
        "אוצר מקולל",
        "קרקן",
        "דרקון",
        "קרברוס",
        "חד קרן",
        "פגסוס",
        "פיה"
      ]
    },
    {
      "id": "mythology_fantasy_038",
      "category_id": "mythology_fantasy",
      "category_name": "מיתולוגיה ופנטזיה",
      "answer": "אביר",
      "answer_niqqud": "אַבִּיר",
      "clues": [
        "אֲנִי מֵעוֹלָם דִּמְיוֹנִי אוֹ מִיתוֹלוֹגִי",
        "אֲנִי לוֹחֵם מְשֻׁרְיָן מִסִּפּוּרֵי יְמֵי הַבֵּינַיִם",
        "לְעִתִּים אֲנִי רוֹכֵב עַל סוּס",
        "מָגֵן וְלַהַב אָרֹךְ קְשׁוּרִים אֵלַי",
        "אֲנִי מְשָׁרֵת שַׁלִּיט אוֹ מַמְלָכָה בְּסִפּוּרִים",
        "הַשִּׁרְיוֹן שֶׁלִּי מְנַצְנֵץ וְכָבֵד לְעִתִּים",
        "אֲנִי מְסַמֵּל כָּבוֹד אֹמֶץ וְנֶאֱמָנוּת",
        "טוּרְנִירִים טִירוֹת וּקְרָבוֹת קְשׁוּרִים אֵלַי",
        "אֲנִי נִשְׁבָּע לְהָגֵן עַל חַלָּשִׁים בְּסִפּוּרִים רַבִּים",
        "זֶה לוֹחֵם בְּשִׁרְיוֹן שֶׁרוֹכֵב עַל סוּס וְנוֹשֵׂא מָגֵן"
      ],
      "grid": [
        "אביר",
        "נסיך",
        "ויקינג",
        "נסיכה",
        "אלה יוונית",
        "מלך",
        "אל יווני",
        "מלכה",
        "שטן",
        "חרב קסומה",
        "מלאך",
        "שרביט קסמים",
        "רוח רפאים",
        "טבעת קסומה",
        "שלד חי",
        "שיקוי קסמים",
        "זומבי",
        "ספר לחשים",
        "מומיה",
        "שער קסום",
        "איש זאב",
        "מבוך",
        "ערפד",
        "אוצר מקולל",
        "גולם",
        "דרקון",
        "בזיליסק",
        "חד קרן",
        "קרקן",
        "פיה",
        "קרברוס",
        "מכשפה"
      ]
    },
    {
      "id": "mythology_fantasy_039",
      "category_id": "mythology_fantasy",
      "category_name": "מיתולוגיה ופנטזיה",
      "answer": "נסיך",
      "answer_niqqud": "נָסִיךְ",
      "clues": [
        "אֲנִי מֵעוֹלָם דִּמְיוֹנִי אוֹ מִיתוֹלוֹגִי",
        "אֲנִי בֶּן לְמִשְׁפָּחָה שׁוֹלֶטֶת בְּסִפּוּרִים רַבִּים",
        "לְעִתִּים אֲנִי גָּר בְּאַרְמוֹן",
        "אֲנִי יָכוֹל לָצֵאת לְמַסָּע כְּדֵי לְהוֹכִיחַ אֹמֶץ",
        "בְּאַגָּדוֹת לְעִתִּים אֲנִי מַצִּיל מִישֶׁהִי אוֹ מִתְחַתֵּן",
        "כֶּתֶר קָטָן וּבְגָדִים מְהֻדָּרִים קְשׁוּרִים אֵלַי",
        "אֲנִי מְסַמֵּל יְרוּשָּׁה מַעֲמָד וְחֻבָה",
        "לְעִתִּים הַדֶּרֶךְ שֶׁלִּי מְלֵאָה מִבְחָנִים וּמִפְלָצוֹת",
        "אֲנִי צָעִיר יַחֲסִית בְּחָצֵר מַמְלָכָה",
        "זֶה בֶּן מְלוּכָה צָעִיר שֶׁמּוֹפִיעַ בְּאַגָּדוֹת"
      ],
      "grid": [
        "נסיך",
        "נסיכה",
        "אביר",
        "מלך",
        "ויקינג",
        "מלכה",
        "אלה יוונית",
        "חרב קסומה",
        "אל יווני",
        "שרביט קסמים",
        "שטן",
        "טבעת קסומה",
        "מלאך",
        "שיקוי קסמים",
        "רוח רפאים",
        "ספר לחשים",
        "שלד חי",
        "שער קסום",
        "זומבי",
        "מבוך",
        "מומיה",
        "אוצר מקולל",
        "איש זאב",
        "דרקון",
        "ערפד",
        "חד קרן",
        "גולם",
        "פיה",
        "בזיליסק",
        "מכשפה",
        "קרקן",
        "קוסם"
      ]
    },
    {
      "id": "mythology_fantasy_040",
      "category_id": "mythology_fantasy",
      "category_name": "מיתולוגיה ופנטזיה",
      "answer": "נסיכה",
      "answer_niqqud": "נְסִיכָה",
      "clues": [
        "אֲנִי מֵעוֹלָם דִּמְיוֹנִי אוֹ מִיתוֹלוֹגִי",
        "אֲנִי בַּת לְמִשְׁפָּחָה שׁוֹלֶטֶת בְּסִפּוּרִים רַבִּים",
        "לְעִתִּים אֲנִי גָּרָה בְּאַרְמוֹן",
        "כֶּתֶר שִׂמְלָה וְחֶדֶר מְהֻדָּר קְשׁוּרִים אֵלַי לְעִתִּים",
        "בְּאַגָּדוֹת אֲנִי יְכוֹלָה לְהִיות כְּלוּאָה אוֹ אַמִּיצָה",
        "אֲנִי מְסַמֶּלֶת מַעֲמָד יֹפִי וְחֲלוֹם לְעִתִּים",
        "סִפּוּרֵי יְלָדִים רַבִּים נִבְנִים סְבִיבִי",
        "לְעִתִּים אֲנִי מְפֵרָה צִפִּיּוֹת וְיוֹצֵאת לְהַרְפַּתְקָה",
        "חֲגִיגָה בָּאַרְמוֹן וְנַעַל מְיֻחֶדֶת קְשׁוּרוֹת לְדִמְיוֹן שֶׁלִּי לְעִתִּים",
        "זֶה בַּת מְלוּכָה מֵאַגָּדוֹת שֶׁל אַרְמוֹנוֹת וּכְתָרִים"
      ],
      "grid": [
        "נסיכה",
        "מלך",
        "נסיך",
        "מלכה",
        "אביר",
        "חרב קסומה",
        "ויקינג",
        "שרביט קסמים",
        "אלה יוונית",
        "טבעת קסומה",
        "אל יווני",
        "שיקוי קסמים",
        "שטן",
        "ספר לחשים",
        "מלאך",
        "שער קסום",
        "רוח רפאים",
        "מבוך",
        "שלד חי",
        "אוצר מקולל",
        "זומבי",
        "דרקון",
        "מומיה",
        "חד קרן",
        "איש זאב",
        "פיה",
        "ערפד",
        "מכשפה",
        "גולם",
        "קוסם",
        "בזיליסק",
        "שדון"
      ]
    },
    {
      "id": "mythology_fantasy_041",
      "category_id": "mythology_fantasy",
      "category_name": "מיתולוגיה ופנטזיה",
      "answer": "מלך",
      "answer_niqqud": "מֶלֶךְ",
      "clues": [
        "אֲנִי מֵעוֹלָם דִּמְיוֹנִי אוֹ מִיתוֹלוֹגִי",
        "אֲנִי שַׁלִּיט מְרָכָּזִי בְּמַמְלָכָה",
        "כֶּתֶר וְכִסֵּא מְפֹאָר קְשׁוּרִים אֵלַי",
        "אֲנִי נוֹתֵן פְּקֻדּוֹת וּמְקַבֵּל שְׁלִיחִים בְּסִפּוּרִים",
        "לְעִתִּים אֲנִי גָּר בְּאַרְמוֹן עִם שׁוֹמְרִים",
        "הַמִּלָּה שֶׁלִּי יְכוֹלָה לְקַבֹּעַ גּוֹרָל שֶׁל מַמְלָכָה",
        "אֲנִי מְסַמֵּל סַמְכוּת כֹּחַ וְאַחְרָיוּת",
        "בְּאַגָּדוֹת אֲנִי יָכוֹל לִהְיוֹת חָכָם אַכְזָר אוֹ מְבֻלְבָּל",
        "הַיְּרוּשָּׁה שֶׁלִּי חֲשׁוּבָה לְדֹרוֹת הַבָּאִים",
        "זֶה שַׁלִּיט עִם כֶּתֶר שֶׁיּוֹשֵׁב עַל כִּסֵּא מְפֹאָר"
      ],
      "grid": [
        "מלך",
        "מלכה",
        "נסיכה",
        "חרב קסומה",
        "נסיך",
        "שרביט קסמים",
        "אביר",
        "טבעת קסומה",
        "ויקינג",
        "שיקוי קסמים",
        "אלה יוונית",
        "ספר לחשים",
        "אל יווני",
        "שער קסום",
        "שטן",
        "מבוך",
        "מלאך",
        "אוצר מקולל",
        "רוח רפאים",
        "דרקון",
        "שלד חי",
        "חד קרן",
        "זומבי",
        "פיה",
        "מומיה",
        "מכשפה",
        "איש זאב",
        "קוסם",
        "ערפד",
        "שדון",
        "גולם",
        "גמד"
      ]
    },
    {
      "id": "mythology_fantasy_042",
      "category_id": "mythology_fantasy",
      "category_name": "מיתולוגיה ופנטזיה",
      "answer": "מלכה",
      "answer_niqqud": "מַלְכָּה",
      "clues": [
        "אֲנִי מֵעוֹלָם דִּמְיוֹנִי אוֹ מִיתוֹלוֹגִי",
        "אֲנִי שַׁלִּיטָה אוֹ דְּמוּת בְּכִירָה בְּמַמְלָכָה",
        "כֶּתֶר וְגְלִימָה מְפֹאֶרֶת קְשׁוּרִים אֵלַי",
        "לְעִתִּים אֲנִי יוֹשֶׁבֶת עַל כִּסֵּא רָם בְּאַרְמוֹן",
        "בְּאַגָּדוֹת אֲנִי יְכוֹלָה לִהְיוֹת טוֹבָה חֲכָמָה אוֹ קַנָּאִית",
        "אֲנִי מְסַמֶּלֶת סַמְכוּת אֵלֶגַנְטִיּוּת וְכֹחַ",
        "יועֲצִים שְׁלִיחִים וְחָצֵר אַרְמוֹן קְשׁוּרִים אֵלַי",
        "לְעִתִּים אֲנִי מְקַבֶּלֶת הַחְלָטוֹת גּוֹרָלִיּוֹת",
        "הַמַּרְאֶה שֶׁלִּי מְהֻדָּר וְרִשְׁמִי בְּסִפּוּרִים",
        "זֶה שַׁלִּיטָה עִם כֶּתֶר בְּאַרְמוֹן"
      ],
      "grid": [
        "מלכה",
        "חרב קסומה",
        "מלך",
        "שרביט קסמים",
        "נסיכה",
        "טבעת קסומה",
        "נסיך",
        "שיקוי קסמים",
        "אביר",
        "ספר לחשים",
        "ויקינג",
        "שער קסום",
        "אלה יוונית",
        "מבוך",
        "אל יווני",
        "אוצר מקולל",
        "שטן",
        "דרקון",
        "מלאך",
        "חד קרן",
        "רוח רפאים",
        "פיה",
        "שלד חי",
        "מכשפה",
        "זומבי",
        "קוסם",
        "מומיה",
        "שדון",
        "איש זאב",
        "גמד",
        "ערפד",
        "ענק"
      ]
    },
    {
      "id": "mythology_fantasy_043",
      "category_id": "mythology_fantasy",
      "category_name": "מיתולוגיה ופנטזיה",
      "answer": "חרב קסומה",
      "answer_niqqud": "חֶרֶב קְסוּמָה",
      "clues": [
        "אֲנִי מֵעוֹלָם דִּמְיוֹנִי אוֹ מִיתוֹלוֹגִי",
        "אֲנִי כְּלִי נֶשֶׁק שֶׁיֵּשׁ לוֹ כֹּחַ פֶּלֶא",
        "לְעִתִּים רַק גִּבּוֹר נִבְחָר יָכוֹל לְהָרִים אוֹתִי",
        "הַלַּהַב שֶׁלִּי יָכוֹל לִזְהֹר בְּאוֹר מְיֻחָד",
        "אֲנִי מוֹפִיעָה בְּמַסָּעוֹת גְּבוּרָה וּבְטִירוֹת עַתִּיקוֹת",
        "לְעִתִּים אֲנִי נִשְׁלֶפֶת מֵאֶבֶן אוֹ נִמְסֶרֶת בְּטֶקֶס",
        "אֲנִי מְסַמֶּלֶת יִעוּד כֹּחַ וְאַחְרָיוּת",
        "בְּקְרָב מוּל רֹעַ גָּדוֹל אֲנִי יְכוֹלָה לְהַכְרִיעַ",
        "הַשֵּׁם שֶׁלִּי נוֹשֵׂא לְעִתִּים אַגָּדָה מִשֶּׁלּוֹ",
        "זֶה לַהַב מֻפְלָא שֶׁרַק גִּבּוֹר מְיֻחָד יָכוֹל לְהַפְעִיל"
      ],
      "grid": [
        "חרב קסומה",
        "שרביט קסמים",
        "מלכה",
        "טבעת קסומה",
        "מלך",
        "שיקוי קסמים",
        "נסיכה",
        "ספר לחשים",
        "נסיך",
        "שער קסום",
        "אביר",
        "מבוך",
        "ויקינג",
        "אוצר מקולל",
        "אלה יוונית",
        "דרקון",
        "אל יווני",
        "חד קרן",
        "שטן",
        "פיה",
        "מלאך",
        "מכשפה",
        "רוח רפאים",
        "קוסם",
        "שלד חי",
        "שדון",
        "זומבי",
        "גמד",
        "מומיה",
        "ענק",
        "איש זאב",
        "טרול"
      ]
    },
    {
      "id": "mythology_fantasy_044",
      "category_id": "mythology_fantasy",
      "category_name": "מיתולוגיה ופנטזיה",
      "answer": "שרביט קסמים",
      "answer_niqqud": "שַׁרְבִיט קְסָמִים",
      "clues": [
        "אֲנִי מֵעוֹלָם דִּמְיוֹנִי אוֹ מִיתוֹלוֹגִי",
        "אֲנִי כְּלִי דַּק שֶׁמְּכַוֵּן כֹּחַ פֶּלֶא",
        "מְנִיפִים אוֹתִי כְּדֵי לְבַצֵּעַ לַחַשׁ",
        "לְעִתִּים נִיצוֹצוֹת יוֹצְאִים מִקְּצֵה הַכְּלִי שֶׁלִּי",
        "אֲנִי נֶאֱחָז בַּיָּד וְלֹא נִלְחָם בְּכֹחַ גּוּפָנִי",
        "בְּבֵית סֵפֶר דִּמְיוֹנִי לְלִמּוּדֵי פֶּלֶא אֲנִי חָשׁוּב מְאֹד",
        "הַחֹמֶר שֶׁלִּי יָכוֹל לִהְיוֹת עֵץ עַתִּיק וּמְיֻחָד",
        "אֲנִי עוֹזֵר לְשַׁנּוֹת לְהָזִיז אוֹ לְהָאִיר דְּבָרִים",
        "בְּסִפּוּרִים רַבִּים אֲנִי מַגִּיב לְבַעַל הַכֹּחַ שֶׁמַּחֲזִיק בִּי",
        "זֶה מַקֵּל קָטָן שֶׁמַּפְעִיל לְחָשִׁים וְנִיצוֹצוֹת"
      ],
      "grid": [
        "שרביט קסמים",
        "טבעת קסומה",
        "חרב קסומה",
        "שיקוי קסמים",
        "מלכה",
        "ספר לחשים",
        "מלך",
        "שער קסום",
        "נסיכה",
        "מבוך",
        "נסיך",
        "אוצר מקולל",
        "אביר",
        "דרקון",
        "ויקינג",
        "חד קרן",
        "אלה יוונית",
        "פיה",
        "אל יווני",
        "מכשפה",
        "שטן",
        "קוסם",
        "מלאך",
        "שדון",
        "רוח רפאים",
        "גמד",
        "שלד חי",
        "ענק",
        "זומבי",
        "טרול",
        "מומיה",
        "גובלין"
      ]
    },
    {
      "id": "mythology_fantasy_045",
      "category_id": "mythology_fantasy",
      "category_name": "מיתולוגיה ופנטזיה",
      "answer": "טבעת קסומה",
      "answer_niqqud": "טַבַּעַת קְסוּמָה",
      "clues": [
        "אֲנִי מֵעוֹלָם דִּמְיוֹנִי אוֹ מִיתוֹלוֹגִי",
        "אֲנִי תַּכְשִׁיט קָטָן עִם כֹּחַ גָּדוֹל",
        "לוֹבְשִׁים אוֹתִי עַל אֶצְבַּע",
        "בְּסִפּוּרִים אֲנִי יְכוֹלָה לְהַעֲנִיק כֹּחַ אוֹ לְהַשְׁחִית",
        "לְעִתִּים כֻּלָּם רוֹצִים לְהַחֲזִיק בִּי",
        "הַמַּרְאֶה שֶׁלִּי פָּשׁוּט אֲבָל הַסּוֹד שֶׁלִּי עָצוּם",
        "אֲנִי קְשׁוּרָה לְמַסָּע וּלְפִתּוּי לְעִתִּים",
        "אֶפְשָׁר לְהַחְבִּיא אוֹתִי בְּכִיס קָטָן אֲבָל קָשֶׁה לְהִתְעַלֵּם מִמֶּנִּי",
        "הַכֹּחַ שֶׁלִּי יָכוֹל לְשַׁנּוֹת גּוֹרָל שֶׁל מַמְלָכוֹת",
        "זֶה עִגּוּל זָהָב קָטָן שֶׁנּוֹשֵׂא כֹּחַ פֶּלֶא גָּדוֹל"
      ],
      "grid": [
        "טבעת קסומה",
        "שיקוי קסמים",
        "שרביט קסמים",
        "ספר לחשים",
        "חרב קסומה",
        "שער קסום",
        "מלכה",
        "מבוך",
        "מלך",
        "אוצר מקולל",
        "נסיכה",
        "דרקון",
        "נסיך",
        "חד קרן",
        "אביר",
        "פיה",
        "ויקינג",
        "מכשפה",
        "אלה יוונית",
        "קוסם",
        "אל יווני",
        "שדון",
        "שטן",
        "גמד",
        "מלאך",
        "ענק",
        "רוח רפאים",
        "טרול",
        "שלד חי",
        "גובלין",
        "זומבי",
        "אורק"
      ]
    },
    {
      "id": "mythology_fantasy_046",
      "category_id": "mythology_fantasy",
      "category_name": "מיתולוגיה ופנטזיה",
      "answer": "שיקוי קסמים",
      "answer_niqqud": "שִׁקּוּי קְסָמִים",
      "clues": [
        "אֲנִי מֵעוֹלָם דִּמְיוֹנִי אוֹ מִיתוֹלוֹגִי",
        "אֲנִי נוֹזֵל מֻפְלָא שֶׁנִּרְקָח בְּזְהִירוּת",
        "לְעִתִּים אֲנִי מְבֻשָּׁל בְּקְדֵרָה מְעַשֶּׁנֶת",
        "רְכִיבִים מוּזָרִים וְנְדִירִים נִזְרָקִים לְתוֹכִי",
        "שְׁתִיָּה מִמֶּנִּי יְכוֹלָה לְשַׁנּוֹת מַרְאֶה אוֹ הַרְגָּשָׁה",
        "הַצֶּבַע שֶׁלִּי יָכוֹל לִהְיוֹת זוהֵר וּמְשֻׁנֶּה",
        "אֲנִי מְסֻכָּן אִם טוֹעִים בַּמִּנּוּן אוֹ בַּמַּתְכּוֹן",
        "בְּסִפּוּרִים אֲנִי יָכוֹל לְרַפֵּא לְהָרְדִּים אוֹ לְהַפֹךְ",
        "בַּקְבּוּק קָטָן עִם פְּקָק יָכוֹל לְהַחֲזִיק אוֹתִי",
        "זֶה נוֹזֵל פֶּלֶא שֶׁרוֹקְחִים וְשׁוֹתִים כְּדֵי לְקַבֵּל הַשְׁפָּעָה מֻזָּרָה"
      ],
      "grid": [
        "שיקוי קסמים",
        "ספר לחשים",
        "טבעת קסומה",
        "שער קסום",
        "שרביט קסמים",
        "מבוך",
        "חרב קסומה",
        "אוצר מקולל",
        "מלכה",
        "דרקון",
        "מלך",
        "חד קרן",
        "נסיכה",
        "פיה",
        "נסיך",
        "מכשפה",
        "אביר",
        "קוסם",
        "ויקינג",
        "שדון",
        "אלה יוונית",
        "גמד",
        "אל יווני",
        "ענק",
        "שטן",
        "טרול",
        "מלאך",
        "גובלין",
        "רוח רפאים",
        "אורק",
        "שלד חי",
        "אלף"
      ]
    },
    {
      "id": "mythology_fantasy_047",
      "category_id": "mythology_fantasy",
      "category_name": "מיתולוגיה ופנטזיה",
      "answer": "ספר לחשים",
      "answer_niqqud": "סֵפֶר לְחָשִׁים",
      "clues": [
        "אֲנִי מֵעוֹלָם דִּמְיוֹנִי אוֹ מִיתוֹלוֹגִי",
        "אֲנִי כְּרָךְ עַתִּיק שֶׁמָּלֵא בְּמִלִּים סוֹדִיּוֹת",
        "הַדַּפִּים שֶׁלִּי יְכוֹלִים לִהְיוֹת צְהֻבִּים וּמְאוּבָּקִים",
        "מִי שֶׁקוֹרֵא בִּי צָרִיךְ לָדַעַת מָה הוּא עוֹשֶׂה",
        "אֲנִי מַכִיל הוֹרָאוֹת לְמַעֲשֵׂי פֶּלֶא",
        "לְעִתִּים אֲנִי נִשְׁמָר בְּמִגְדָּל אוֹ בְּסִפְרִיָּה סוֹדִית",
        "סִמָּנִים עַתִּיקִים וְשָׂפָה מֻזָּרָה מוֹפִיעִים בִּי",
        "אֲנִי יָכוֹל לְהָיוֹת אָסוּר לִקְרִיאָה לְתַלְמִידִים צְעִירִים",
        "כְּרִיכָה כְּבֵדָה וְנֵרוֹת דּוֹלְקִים מַתְאִימִים לִי",
        "זֶה כְּרָךְ קֶסֶם שֶׁכְּתוּבִים בּוֹ לְחָשִׁים וְטְקָסִים"
      ],
      "grid": [
        "ספר לחשים",
        "שער קסום",
        "שיקוי קסמים",
        "מבוך",
        "טבעת קסומה",
        "אוצר מקולל",
        "שרביט קסמים",
        "דרקון",
        "חרב קסומה",
        "חד קרן",
        "מלכה",
        "פיה",
        "מלך",
        "מכשפה",
        "נסיכה",
        "קוסם",
        "נסיך",
        "שדון",
        "אביר",
        "גמד",
        "ויקינג",
        "ענק",
        "אלה יוונית",
        "טרול",
        "אל יווני",
        "גובלין",
        "שטן",
        "אורק",
        "מלאך",
        "אלף",
        "רוח רפאים",
        "בת ים"
      ]
    },
    {
      "id": "mythology_fantasy_048",
      "category_id": "mythology_fantasy",
      "category_name": "מיתולוגיה ופנטזיה",
      "answer": "שער קסום",
      "answer_niqqud": "שַׁעַר קָסוּם",
      "clues": [
        "אֲנִי מֵעוֹלָם דִּמְיוֹנִי אוֹ מִיתוֹלוֹגִי",
        "אֲנִי פֶּתַח שֶׁמּוֹבִיל לְמָקוֹם אַחֵר בְּדֶרֶךְ פֶּלֶא",
        "לְעִתִּים אֲנִי נִפְתָּח רַק בְּמִלָּה סוֹדִית",
        "מִי שֶׁעוֹבֵר דַּרְכִּי יָכוֹל לְהַגִּיעַ לְעוֹלָם רָחוֹק",
        "אֲנִי יָכוֹל לְהִסְתַּתֵּר בְּמַרְאָה בְּקִיר אוֹ בֵּין עֵצִים",
        "אוֹר מִסְתּוֹבֵב וְרַעַד קַל מְלַוִּים אוֹתִי לְעִתִּים",
        "אֲנִי מְקַצֵּר מֶרְחָק שֶׁאִי אֶפְשָׁר לַעֲבֹר בְּרֶגֶל",
        "בְּסִפּוּרֵי הַרְפַּתְקָה אֲנִי מַתְחִיל פֶּרֶק חָדָשׁ",
        "לְעִתִּים אֲנִי נִסְגָּר מִיָּד אַחֲרֵי הַמַּעֲבָר",
        "זֶה פֶּתַח פֶּלֶא שֶׁמַּעֲבִיר בִּרְגַע לְעוֹלָם אַחֵר"
      ],
      "grid": [
        "שער קסום",
        "מבוך",
        "ספר לחשים",
        "אוצר מקולל",
        "שיקוי קסמים",
        "דרקון",
        "טבעת קסומה",
        "חד קרן",
        "שרביט קסמים",
        "פיה",
        "חרב קסומה",
        "מכשפה",
        "מלכה",
        "קוסם",
        "מלך",
        "שדון",
        "נסיכה",
        "גמד",
        "נסיך",
        "ענק",
        "אביר",
        "טרול",
        "ויקינג",
        "גובלין",
        "אלה יוונית",
        "אורק",
        "אל יווני",
        "אלף",
        "שטן",
        "בת ים",
        "מלאך",
        "קנטאור"
      ]
    },
    {
      "id": "mythology_fantasy_049",
      "category_id": "mythology_fantasy",
      "category_name": "מיתולוגיה ופנטזיה",
      "answer": "מבוך",
      "answer_niqqud": "מָבוֹךְ",
      "clues": [
        "אֲנִי מֵעוֹלָם דִּמְיוֹנִי אוֹ מִיתוֹלוֹגִי",
        "אֲנִי מָקוֹם מְבֻלְבָּל שֶׁקָּשֶׁה לָצֵאת מִמֶּנּוּ",
        "יֵשׁ בִּי שְׁבִילִים פְּנִיּוֹת וּדְרָכִים לְלֹא מוֹצָא",
        "גִּבּוֹרִים נִכְנָסִים אֵלַי וְצְרִיכִים חָכְמָה כְּדֵי לָצֵאת",
        "לְעִתִּים מִפְלֶצֶת אוֹ אוֹצָר מִסְתַּתְּרִים בְּתוֹכִי",
        "מַפָּה אוֹ חוּט יְכוֹלִים לַעֲזֹר בִּי",
        "אֲנִי יָכוֹל לִהְיוֹת מִשִּׂיחִים קִירוֹת אוֹ אֶבֶן",
        "כָּל פְּנִיָּה בִּי יְכוֹלָה לִהְיוֹת נְכוֹנָה אוֹ מַטְעָה",
        "אֲנִי מְסַמֵּל חִידָה גְּדוֹלָה וְחִפּוּשׂ דֶּרֶךְ",
        "זֶה מַעֲרֶכֶת דְּרָכִים מְבֻלְבֶּלֶת עִם הַרְבֵּה מַסְלוּלֵי סְרָק"
      ],
      "grid": [
        "מבוך",
        "אוצר מקולל",
        "שער קסום",
        "דרקון",
        "ספר לחשים",
        "חד קרן",
        "שיקוי קסמים",
        "פיה",
        "טבעת קסומה",
        "מכשפה",
        "שרביט קסמים",
        "קוסם",
        "חרב קסומה",
        "שדון",
        "מלכה",
        "גמד",
        "מלך",
        "ענק",
        "נסיכה",
        "טרול",
        "נסיך",
        "גובלין",
        "אביר",
        "אורק",
        "ויקינג",
        "אלף",
        "אלה יוונית",
        "בת ים",
        "אל יווני",
        "קנטאור",
        "שטן",
        "מינוטאור"
      ]
    },
    {
      "id": "mythology_fantasy_050",
      "category_id": "mythology_fantasy",
      "category_name": "מיתולוגיה ופנטזיה",
      "answer": "אוצר מקולל",
      "answer_niqqud": "אוֹצָר מְקֻלָּל",
      "clues": [
        "אֲנִי מֵעוֹלָם דִּמְיוֹנִי אוֹ מִיתוֹלוֹגִי",
        "אֲנִי עֲרֵמָה מְפֹאֶרֶת שֶׁמַּבְטִיחָה עֹשֶׁר וְסַכָּנָה",
        "זָהָב אֲבָנִים יְקָרוֹת וְתֵבָה עַתִּיקָה קְשׁוּרִים אֵלַי",
        "מִי שֶׁלוֹקֵחַ אוֹתִי עָלוּל לְשַׁלֵּם מְחִיר כָּבֵד",
        "לְעִתִּים אֲנִי מֻחְבָּא בְּמְעָרָה בְּסְפִינָה אוֹ בְּמִקְדָּשׁ",
        "מַפָּה יְשָׁנָה מוֹבִילָה אֵלַי בְּסִפּוּרֵי הַרְפַּתְקָה",
        "שׁוֹמְרִים מְלַכֹּדוֹת וּסְמָלִים מוּזָרִים מְגִנִּים עָלַי",
        "אֲנִי מְפַתֶּה גִּבּוֹרִים לְהַמְשִׁיךְ לְמָקוֹם מְסֻכָּן",
        "הַבְּרָק שֶׁלִּי מַסְתִּיר בְּעָיָה אֲפֵלָה",
        "זֶה רְכוּשׁ יָקָר שֶׁמֵּבִיא עֹשֶׁר וְאָסוֹן לְמִי שֶׁנוֹגֵעַ בּוֹ"
      ],
      "grid": [
        "אוצר מקולל",
        "דרקון",
        "מבוך",
        "חד קרן",
        "שער קסום",
        "פיה",
        "ספר לחשים",
        "מכשפה",
        "שיקוי קסמים",
        "קוסם",
        "טבעת קסומה",
        "שדון",
        "שרביט קסמים",
        "גמד",
        "חרב קסומה",
        "ענק",
        "מלכה",
        "טרול",
        "מלך",
        "גובלין",
        "נסיכה",
        "אורק",
        "נסיך",
        "אלף",
        "אביר",
        "בת ים",
        "ויקינג",
        "קנטאור",
        "אלה יוונית",
        "מינוטאור",
        "אל יווני",
        "קיקלופ"
      ]
    }
  ]
}